Workbook

Sheet 填写说明（请仔细查阅！！！）
A2: 序号 | B2: 对应细项 | C2: 填写说明
A3: 1 | B3: 报价单命名 | C3: 项目名称+供应商简称+报价日期+项目总金额
A4: 2 | B4: 报价单提供格式 | C4: 电子表格版+盖章扫描件。 此报价单必须加盖印章（公章、合同专用章、报价专用章，其中优先选择公章）,根据询价单位要求提供盖章扫描件或原件。
A5: 3 | B5: 项目时间 | C5: 需填写已知的项目执行时间
A6: 4 | B6: 报价公司名称 | C6: 需填写供应商全称
A7: 5 | B7: 报价项目 | C7: 需与招采通知的项目名称一致。
A8: 6 | B8: 报价人姓名 | C8: 填写真实提供报价的人员姓名，需与身份证上姓名一致
A9: 7 | B9: 报价人联系电话 | C9: 填写手机号
A10: 8 | B10: 报价人邮箱 | C10: 填写正确邮箱信息，原则上要求使用供应商公司邮箱
A11: 9 | B11: 行数量 | C11: 行数量和信息，可以根据实际情况调整。
A12: 10 | B12: 年框编号 | C12: 非年度供应商不需要填写年框编号。
A13: 11 | B13: 一线&二线城市报价 | C13: 如项目仅为一线或二线城市，按照报价模板进行常规报价即可； 如一个整包项目里包含多城市报价，报名明细页分为一线&二线城市两个表。
A14: 12 | B14: sku | C14: 无需罗列全部签约sku价格，根据实际使用sku项进行填写
A15: 注意！！！ （1）报价严格按照SKU进行提报拆分，SKU号+SKU描述+SKU价格，三个必须严格统一，采购会严格复核。 （2）支付凭证最好为支付/打款记录，虚假凭证一经发现，永久停止合作
A16: 具体填写说明：“汇总页”以下各部分如果没有，可以在报价单中留白，但是不要删除。
A17: 1 | B17: 指定垫付部分 | C17: 如中途接到需求部门自行指定分包或垫付要求，需要同步告知招采，招采确认推进方式后再进行推进；
A18: 2 | B18: 场地租赁部分 | C18: （1）原则上，场地租赁费用等不由供应商垫付。场地公关报批等现金类小额支付，可由供应商垫付。 （2）如因特殊情况，经招采确认可由供应商支付，此部分需供应商明确场地名称，具体展会位置/酒店会议厅等、面积、使用时段等信息。
A19: 3 | B19: 场地杂项部分 | C19: （1）场地相关的水电网、施工证、停车费等，可根据实际项目情况由供应商垫付，提供相应的凭证。
A20: 4 | B20: 搭建物料及人员部分 | C20: （1）搭建物料部分明确材质、工艺、尺寸。如报价中计算损耗，需对损耗部分说明。 （2）搭建人工明确进场/撤场时间（以*月*日*点）、以及工时。 （3) 搭建运输：明确车型、距离。运输费用：需要提供支付凭证结算，如为搭建物料公司负责，需要提供现场带日期地点水印的车辆照片
A21: 5 | B21: AV设备及人员部分 | C21: （1）所有设备具体到最小单位并标明品牌型号。特殊不常用的非年框设备，需标明用途。 （2）所有AV相关的人工，明确工种、工时。
A22: 6 | B22: 第三方人员部分 | C22: （1）兼职、保安、礼仪、模特、演员、摄影、摄像等，工作的人数、时长。 （2）非年框等级的化妆师、搭配师、摄影摄像师、模特、秀导、主持人、演员等提供姓名及简介。 （3） 机票、酒店、交通费等，列明时间、地点、人次、费用（执行京东的项目，国内机票酒店原则上使用京东商旅）
A23: 7 | B23: 后勤杂项部分 | C23: （1）小物料（抽奖箱、水牌、画架、椅背贴、指示牌、桌卡等）、奖杯等明确材质、尺寸。 （2）快递费：京东的项目，原则上使用京东快递。
A24: 8 | B24: 视频部分 | C24: 写清楚视频的片长、大致类型，主要内容等。 严格按照SKU细项进行报价，框外内容请说明背景原因。
A25: 9 | B25: 创意策划执行部分 | C25: （1）执行人员差旅当地交通：需要提供凭证 （2）执行人员差旅当地餐补：需要提供凭证 （3）执行人员差旅住宿费用：需要提供凭证且严格按照标准进行费用提报，不能超标准！
A26: 10 | B26: 差旅部分 | C26: 原则上使用京东商旅，尤其是国内机票。 如未使用京东商旅，请在项目执行前与采购员确认。（京东人员差旅不允许由供应商支付）
A27: 11 | B27: 展品物流部分 | C27: （1）车辆租用：需要提供支付凭证结算 （2）运输费用：需要提供支付凭证结算
A28: 12 | B28: 其他部分 | C28: 根据实际情况填写，涉及到第三方的，均需列明详细信息。
A29: 13 | B29: 城市清单 | C29: 一线城市报价挡：4个，北京市，上海市，广州市，深圳市； 二线城市报价挡：45个，成都市，杭州市，武汉市，重庆市，南京市，天津市，苏州市，西安市，长沙市，沈阳市，青岛市，郑州市，大连市，东莞市，宁波市，厦门市，福州市，无锡市，合肥市，昆明市，哈尔滨市，济南市，佛山市，长春市，温州市，石家庄市，南宁市，常州市，泉州市，南昌市，贵阳市，太原市，烟台市，嘉兴市，南通市，金华市，珠海市，惠州市，徐州市，海口市，乌鲁木齐市，绍兴市，中山市，台州市，兰州市

Sheet 汇总页模板
A1: 报价阶段-投标阶段 | F1: 报价阶段-执行前定标阶段 | K1: 报价阶段-执行后结算阶段
A2: 报价项目 | B2: 图书开学季&9.2超品日 | F2: 报价项目 | G2: 图书开学季&9.2超品日 | K2: 报价项目 | L2: 图书开学季&9.2超品日
A3: 项目时间 | B3: 2025年8月30-31日 | F3: 项目时间 | G3: 2025年8月30-31日 | K3: 项目时间 | L3: 2025年8月30-31日
A4: 报价公司名称 | B4: 成都申逻商务信息咨询有限公司 | F4: 报价公司名称 | G4: 成都申逻商务信息咨询有限公司 | K4: 报价公司名称 | L4: 成都申逻商务信息咨询有限公司
A5: 各部分内容 | B5: 描述 | C5: 报价金额 | D5: 备注 | F5: 各部分内容 | G5: 描述 | H5: 报价金额 | I5: 备注 | K5: 各部分内容 | L5: 描述 | M5: 报价金额 | N5: 备注
A6: 指定垫付部分 | C6: 0 | D6: 需求部门指定垫付 | F6: 指定垫付部分 | H6: 0 | I6: 需求部门指定垫付 | K6: 指定垫付部分 | M6: 0 | N6: 需求部门指定垫付
A7: 场地租赁部分 | C7: 0 | D7: 场地租赁 | F7: 场地租赁部分 | H7: 0 | I7: 场地租赁 | K7: 场地租赁部分 | M7: 0 | N7: 场地租赁
A8: 场地杂项部分 | C8: 12000 | D8: 包含报批、安保、网络、水电等 | F8: 场地杂项部分 | H8: =明细页模板!X18 -> 2000 | I8: 包含报批、安保、网络、水电等 | K8: 场地杂项部分 | M8: =明细页模板!AN16 -> 2000 | N8: 包含报批、安保、网络、水电等
A9: 搭建物料及人员部分 | C9: 102573.2 | D9: 包含搭建制作物料、力工、水工、电工等 | F9: 搭建物料及人员部分 | H9: =明细页模板!X86 -> 63393.969 | I9: 包含搭建制作物料、力工、水工、电工等 | K9: 搭建物料及人员部分 | M9: =明细页模板!AN56 -> 63953.969 | N9: 包含搭建制作物料、力工、水工、电工等
A10: AV设备及人员部分 | C10: 9364.68 | D10: 包含视频、灯光、音频相关设备及配套人员等 | F10: AV设备及人员部分 | H10: =明细页模板!X93 -> 1600 | I10: 包含视频、灯光、音频相关设备及配套人员等 | K10: AV设备及人员部分 | M10: =明细页模板!AN59 -> 1600 | N10: 包含视频、灯光、音频相关设备及配套人员等
A11: 第三方人员部分 | C11: 12573.21 | D11: 包含主持人、礼仪、保安、摄影摄像等 | F11: 第三方人员部分 | H11: =明细页模板!X101 -> 12573.21 | I11: 包含主持人、礼仪、保安、摄影摄像等 | K11: 第三方人员部分 | M11: =明细页模板!AN71 -> 12553.21 | N11: 包含主持人、礼仪、保安、摄影摄像等
A12: 后勤杂项部分 | C12: 0 | D12: 包含小物料等 | F12: 后勤杂项部分 | H12: =明细页模板!X112 -> 11416 | I12: 包含小物料等 | K12: 后勤杂项部分 | M12: =明细页模板!AN88 -> 12013.56 | N12: 包含小物料等
A13: 视频部分 | C13: 0 | D13: 包含视频制作剪辑等 | F13: 视频部分 | H13: =明细页模板!X116 -> 0 | I13: 包含视频制作剪辑等 | K13: 视频部分 | M13: =明细页模板!AN92 -> 0 | N13: 包含视频制作剪辑等
A14: 创意策划执行部分 | C14: 8127.79 | D14: 包含主视觉涉及、延展、执行人员费用等 | F14: 创意策划执行部分 | H14: =明细页模板!X123 -> 7712.705 | I14: 包含主视觉涉及、延展、执行人员费用等 | K14: 创意策划执行部分 | M14: =明细页模板!AN97 -> 2186.44 | N14: 包含主视觉涉及、延展、执行人员费用等
A15: 差旅部分 | C15: 6000 | D15: 包含执行人员差旅等 | F15: 差旅部分 | H15: =明细页模板!X126 -> 4000 | I15: 包含执行人员差旅等 | K15: 差旅部分 | M15: =明细页模板!AN100 -> 2460 | N15: 包含执行人员差旅等
A16: 展品物流部分 | C16: 30000 | D16: 包含供应商安排车辆进行展品运输等 | F16: 展品物流部分 | H16: =明细页模板!X129 -> 3000 | I16: 包含供应商安排车辆进行展品运输等 | K16: 展品物流部分 | M16: =明细页模板!AN103 -> 308.2 | N16: 包含供应商安排车辆进行展品运输等
A17: 其他部分 | C17: 19416 | F17: 其他部分 | H17: =明细页模板!X132 -> 0 | K17: 其他部分 | M17: =明细页模板!AN106 -> 0
A18: 小计(一线城市) | C18: 48543.79 | D18: 包含北京、上海、广州、深圳 | F18: 小计(一线城市) | H18: =明细页模板!X133 -> 28128.705 | I18: 包含北京、上海、广州、深圳 | K18: 小计(一线城市) | M18: =明细页模板!AN107 -> 18968.2 | N18: 包含北京、上海、广州、深圳
A19: 小计(二线城市) | B19: 一线城市报价*90% | C19: 112059.98 | D19: 包含约定的45个二线城市 | F19: 小计(二线城市) | G19: 一线城市报价*90% | H19: =明细页模板!X134 -> 69810.462 | I19: 包含约定的45个二线城市 | K19: 小计(二线城市) | L19: 一线城市报价*90% | M19: =明细页模板!AN108 -> 70296.462 | N19: 包含约定的45个二线城市
A20: 服务费 | B20: 0.1 | C20: =(C18+C19)*B20 -> 16060.377 | F20: 服务费 | H20: =明细页模板!X135 -> 9793.9167 | K20: 服务费 | M20: =明细页模板!AN109 -> 8926.4662
A21: 税费 | B21: 0.06 | C21: =(C18+C19+C20)*B21 -> 10599.849 | F21: 税费 | H21: =明细页模板!X136 -> 6463.985 | K21: 税费 | M21: =明细页模板!AN110 -> 5891.4677
A22: 总价 | C22: =C18+C19+C20+C21 -> 187264 | F22: 总价 | H22: =明细页模板!X137 -> 114197.07 | K22: 总价 | M22: =明细页模板!AN111 -> 104082.6
A23: 优惠价 | F23: 优惠价 | K23: 优惠价 | M23: 104000 | N23: 优惠后按照104,000元结算
F25: 变更小结 | K25: 变更小结
F26: 执行前定标价格 vs. 投标阶段预中标价格 | K26: 执行后结算价格 vs. 执行前定标价格
F27: 新增需求内容 | I27: =SUMIF(明细页模板!Z$8:Z$129,F27:F30,明细页模板!Y$8:Y$129) -> 45309.387 | K27: 新增需求内容 | M27: =SUMIF(明细页模板!AP$8:AP$103,K27:K30,明细页模板!AO$8:AO$103) -> 1984.47
F28: 取消需求内容 | I28: =SUMIF(明细页模板!Z$8:Z$129,F27:F30,明细页模板!Y$8:Y$129) -> -93652.084 | K28: 取消需求内容 | M28: =SUMIF(明细页模板!AP$8:AP$103,K27:K30,明细页模板!AO$8:AO$103) -> -300
F29: 变更需求内容-导致费用增加 | I29: =SUMIF(明细页模板!Z$8:Z$129,F27:F30,明细页模板!Y$8:Y$129) -> -782.86811 | K29: 变更需求内容-导致费用增加 | M29: =SUMIF(明细页模板!AP$8:AP$103,K27:K30,明细页模板!AO$8:AO$103) -> 0
F30: 变更需求内容-导致费用减少 | I30: =SUMIF(明细页模板!Z$8:Z$129,F27:F30,明细页模板!Y$8:Y$129) -> -8342.3362 | K30: 变更需求内容-导致费用减少 | M30: =SUMIF(明细页模板!AP$8:AP$103,K27:K30,明细页模板!AO$8:AO$103) -> -2700.28

Sheet 明细页模板
A1: 报价阶段-投标阶段 | N1: 报价阶段-执行前定标阶段 | AD1: 报价阶段-执行后结算阶段
A2: 报价项目 | C2: 京东图书开学季 | N2: 报价项目 | P2: 京东图书开学季 | AD2: 报价项目 | AF2: 京东图书开学季
A3: 项目时间 | C3: 2025年8月30-31日 | N3: 项目时间 | P3: 2025年8月30-31日 | AD3: 项目时间 | AF3: 2025年8月30-31日
A4: 报价公司名称 | C4: 成都申逻商务信息咨询有限公司 | N4: 报价公司名称 | P4: 成都申逻商务信息咨询有限公司 | AD4: 报价公司名称 | AF4: 成都申逻商务信息咨询有限公司
A5: 报价人姓名 | C5: 王茜 | D5: 报价人联系电话 | E5: 18054795309 | F5: 报价人邮箱 | G5: shirly.wang@sensel.team | N5: 报价人姓名 | P5: 王茜 | Q5: 报价人联系电话 | R5: 18054795309 | S5: 报价人邮箱 | T5: shirly.wang@sensel.team | AD5: 报价人姓名 | AF5: 王茜 | AG5: 报价人联系电话 | AH5: 18054795309 | AI5: 报价人邮箱 | AJ5: shirly.wang@sensel.team
A6: 具体报价内容 | N6: 具体报价内容 | AD6: 具体报价内容
A7: 序号 | B7: 项目分项 | C7: 年框编号 *非框则为空 | D7: 项目明细 | E7: 具体明细（工艺/内容/规格） | F7: 数量 | G7: 数量单位 | H7: 时间 | I7: 时间单位 | J7: 单价 | K7: 金额 | L7: 备注 如有垫付或者要求提供凭证项，备注”提供凭证实报实销“ | N7: 序号 | O7: 项目分项 | P7: 年框编号 *非框则为空 | Q7: 项目明细 | R7: 具体明细（工艺/内容/规格） | S7: 数量 | T7: 数量单位 | U7: 时间 | V7: 时间单位 | W7: 单价 | X7: 金额 | Y7: 变更金额 | Z7: 变更状态 | AA7: 变更说明 | AB7: 备注 如有垫付或者要求提供凭证项，备注”提供凭证实报实销“ | AD7: 序号 | AE7: 项目分项 | AF7: 年框编号 *非框则为空 | AG7: 项目明细 | AH7: 具体明细（工艺/内容/规格） | AI7: 数量 | AJ7: 数量单位 | AK7: 时间 | AL7: 时间单位 | AM7: 单价 | AN7: 金额 | AO7: 变更金额 | AP7: 变更状态 | AQ7: 变更说明 | AR7: 备注 如有垫付或者要求提供凭证，请按照顺利整理相关凭证并编号，下方对应注明；凭证整体打包压缩后发送提供； 示例：凭证1-礼品购买XXX元 示例：凭证2-场地垫付XXX元
A8: 1 | B8: 指定垫付部分 | N8: 1 | O8: 指定垫付部分 | AD8: 1 | AE8: 指定垫付部分 | AO8: =X8-AN8 -> 0
A9: 2 | B9: 。。。 | N9: 2 | AD9: 2
A10: 3 | B10: 指定垫付部分小计 | C10: \ | D10: \ | E10: \ | F10: \ | G10: \ | H10: \ | I10: \ | J10: \ | K10: =SUM(K8:K9) -> 0 | N10: 3 | O10: 指定垫付部分小计 | P10: \ | Q10: \ | R10: \ | S10: \ | T10: \ | U10: \ | V10: \ | W10: \ | X10: 0 | AD10: 3 | AE10: 指定垫付部分小计 | AF10: \ | AG10: \ | AH10: \ | AI10: \ | AJ10: \ | AK10: \ | AL10: \ | AM10: \ | AO10: 0 | AP10: 0 | AQ10: 0
A11: 4 | B11: 场地租赁部分 | N11: 4 | O11: 场地租赁部分 | AD11: 4
A12: 5 | B12: 。。。 | N12: 5 | O12: 场地租赁部分 | AD12: 5
A13: 6 | B13: 场地租赁部分小计 | C13: \ | D13: \ | E13: \ | F13: \ | G13: \ | H13: \ | I13: \ | J13: \ | K13: 0 | N13: 6 | O13: 场地租赁部分小计 | P13: \ | Q13: \ | R13: \ | S13: \ | T13: \ | U13: \ | V13: \ | W13: \ | X13: 0 | AD13: 6 | AE13: 场地租赁部分小计 | AF13: \ | AG13: \ | AH13: \ | AI13: \ | AJ13: \ | AK13: \ | AL13: \ | AM13: \ | AO13: 0 | AP13: 0 | AQ13: 0
A14: 7 | B14: 场地电费支出 | E14: 场地电费，1元/度 | F14: 1 | G14: 项 | H14: 2 | I14: 天 | J14: 500 | K14: =F14*H14*J14 -> 1000 | L14: 场地电费，据实结算 | N14: 7 | O14: 场地电费支出 | R14: 场地电费，1元/度 | S14: 0 | T14: 项 | U14: 0 | V14: 天 | W14: 0 | X14: =S14*U14*W14 -> 0 | Y14: =X14-K14 -> -1000 | Z14: 取消需求内容 | AD14: 7 | AE14: 场地保险费用 | AH14: 保险采买 | AI14: 1 | AJ14: 项 | AK14: 1 | AL14: 天 | AM14: 2000 | AN14: =AI14*AK14*AM14 -> 2000 | AO14: =AN14-X15 -> 0 | AR14: 凭证12
A15: 8 | B15: 场地保险费用 | E15: 保险采买 | F15: 1 | G15: 项 | H15: 1 | I15: 天 | J15: 3000 | K15: =F15*H15*J15 -> 3000 | L15: 保险费用预留，据实结算 | N15: 8 | O15: 场地保险费用 | R15: 保险采买 | S15: 1 | T15: 项 | U15: 1 | V15: 天 | W15: 2000 | X15: =S15*U15*W15 -> 2000 | Y15: =X15-K15 -> -1000 | Z15: 变更需求内容-导致费用增加 | AB15: 提供凭证实报实销 | AD15: 8
A16: 9 | B16: 场地安评报告 | E16: 场地安评报告提供 | F16: 1 | G16: 项 | H16: 1 | I16: 天 | J16: 8000 | K16: =F16*H16*J16 -> 8000 | L16: 场地报备安评报告费用 | N16: 9 | O16: 场地安评报告 | R16: 场地安评报告提供 | S16: 0 | T16: 项 | U16: 0 | V16: 天 | W16: 0 | X16: =S16*U16*W16 -> 0 | Y16: =X16-K16 -> -8000 | Z16: 取消需求内容 | AD16: 9 | AE16: 场地杂项部分小计 | AF16: \ | AG16: \ | AH16: \ | AI16: \ | AJ16: \ | AK16: \ | AL16: \ | AM16: \ | AN16: =SUM(AN14:AN14) -> 2000 | AO16: =SUM(AO14:AO14) -> 0 | AP16: 0 | AQ16: 0
A17: 10 | B17: 。。。 | N17: 10 | O17: 场地杂项部分 | AD17: 10 | AE17: 点位地贴 | AF17: JT0807010250026 | AG17: 搭建部分-写真喷绘 | AH17: 搭建部分-写真喷绘 高清画面地贴 黑底带背胶表面覆地膜，1.5m宽幅，130g高精度喷印/裱亚膜 制作 | AI17: 124.81 | AJ17: 平方米 | AK17: 1 | AL17: 天 | AM17: 80 | AN17: =AI17*AK17*AM17 -> 9984.8 | AO17: =AN17-X20 -> 0
A18: 11 | B18: 场地杂项部分小计 | C18: \ | D18: \ | E18: \ | F18: \ | G18: \ | H18: \ | I18: \ | J18: \ | K18: =SUM(K14:K17) -> 12000 | N18: 11 | O18: 场地杂项部分小计 | P18: \ | Q18: \ | R18: \ | S18: \ | T18: \ | U18: \ | V18: \ | W18: \ | X18: =SUM(X14:X16) -> 2000 | Y18: =SUM(Y14:Y16) -> -10000 | AD18: 11 | AE18: 主dp-结构 | AF18: JT0807010100009 | AG18: 搭建部分-背景结构 | AH18: 搭建部分-背景结构 木质背板 异形单面木质背景板/木结构，表面防火板，正面裱写真，含支撑及画面 制作 | AI18: 26.4 | AJ18: 平方米 | AK18: 1 | AL18: 天 | AM18: 235.84906 | AN18: =AI18*AK18*AM18 -> 6226.4151 | AO18: =AN18-X22 -> 0
A19: 12 | B19: 点位地贴 | C19: JT0807010250023 | D19: 搭建部分-写真喷绘 | E19: 搭建部分-写真喷绘 斜纹地贴 常规规格 制作 | F19: 120 | G19: 平方米 | H19: 1 | I19: 天 | J19: 70 | K19: =F19*H19*J19 -> 8400 | L19: 地贴尺寸:12*10=120㎡ | N19: 12 | O19: 点位地贴 | P19: JT0807010250023 | Q19: 搭建部分-写真喷绘 | R19: 搭建部分-写真喷绘 斜纹地贴 常规规格 制作 | S19: 0 | T19: 平方米 | U19: 0 | V19: 天 | W19: 70 | X19: =S19*U19*W19 -> 0 | Y19: =X19-K19 -> -8400 | Z19: 取消需求内容 | AA19: 设计定稿后更新材质及尺寸 | AD19: 12 | AE19: 主dp-装饰画面 | AF19: JT0807010250017 | AG19: 搭建部分-写真喷绘 | AH19: 搭建部分-写真喷绘 写真喷绘 PVC板/裱高清,5MM板，含覆膜/常规规格 制作 | AI19: 5 | AJ19: 平方米 | AK19: 1 | AL19: 天 | AM19: 80 | AN19: =AI19*AK19*AM19 -> 400 | AO19: =AN19-X24 -> 0
A20: 13 | B20: 主dp-结构 | C20: JT0807010100010 | D20: 搭建部分-背景结构 | E20: 搭建部分-背景结构 木质背板 双面木质涂料背板/木结构，表面刷涂料，含支撑 制作 | F20: 48 | G20: 平方米 | H20: 1 | I20: 天 | J20: 295 | K20: =F20*H20*J20 -> 14160 | L20: 设计未定，尺寸预估；2*(4.2*2.5+2.5*1.2+4.2*1.2)=38.58㎡, 书本左上结构做热弯工艺,尺寸及耗材会增加,合计为48㎡ | N20: 13 | O20: 点位地贴 | P20: JT0807010250026 | Q20: 搭建部分-写真喷绘 | R20: 搭建部分-写真喷绘 高清画面地贴 黑底带背胶表面覆地膜，1.5m宽幅，130g高精度喷印/裱亚膜 制作 | S20: 124.81 | T20: 平方米 | U20: 1 | V20: 天 | W20: 80 | X20: =S20*U20*W20 -> 9984.8 | Y20: =X20-0 -> 9984.8 | Z20: 新增需求内容 | AA20: 设计定稿后更新材质及尺寸 | AB20: 大地贴：尺寸 长12.69m 宽9.52 面积计算：12.69*9.52=120.81m²； 小地贴：尺寸 长2m 宽2m 2*2=4m，小计124.81m² | AD20: 13 | AE20: 主dp-支撑 | AF20: JT0807010190017 | AG20: 搭建部分-基础结构 | AH20: 搭建部分-基础结构 钢结构 30*30方钢 制作 | AI20: 9.42 | AJ20: 米 | AK20: 1 | AL20: 天 | AM20: 39.839623 | AN20: =AI20*AK20*AM20 -> 375.28925 | AO20: =AN20-X25 -> 0
A21: 14 | B21: 主dp-画面 | C21: JT0807010250006 | D21: 搭建部分-写真喷绘 | E21: 搭建部分-写真喷绘 写真喷绘 进口3M车贴 /常规规格 制作 | F21: 38.58 | G21: 平方米 | H21: 1 | I21: 天 | J21: 60.377358 | K21: =F21*H21*J21 -> 2329.3585 | L21: 设计未定，尺寸预估；2(4.2*2.5+2.5*1+4.2*1)=35㎡ | N21: 14 | O21: 主dp-结构 | P21: JT0807010100010 | Q21: 搭建部分-背景结构 | R21: 搭建部分-背景结构 木质背板 双面木质涂料背板/木结构，表面刷涂料，含支撑 制作 | S21: 0 | T21: 平方米 | U21: 1 | V21: 天 | W21: 295 | X21: =S21*U21*W21 -> 0 | Y21: =X21-K20 -> -14160 | Z21: 取消需求内容 | AA21: 设计定稿后更新材质及尺寸 | AD21: 14 | AE21: 主dp-底座结构 | AF21: JT0807010100006 | AG21: 搭建部分-背景结构 | AH21: 搭建部分-背景结构 木质背板 异形单面木质涂料背板/木结构，表面刷涂料，含支撑 制作 | AI21: 10.56 | AJ21: 平方米 | AK21: 1 | AL21: 天 | AM21: 240 | AN21: =AI21*AK21*AM21 -> 2534.4 | AO21: =AN21-X27 -> 0
A22: 15 | B22: 主dp-装饰画面 | C22: JT0807010250017 | D22: 搭建部分-写真喷绘 | E22: 搭建部分-写真喷绘 写真喷绘 PVC板/裱高清,5MM板，含覆膜/常规规格 制作 | F22: 8 | G22: 平方米 | H22: 1 | I22: 天 | J22: 80 | K22: =F22*H22*J22 -> 640 | L22: 装饰雪弗板画面 | N22: 15 | O22: 主dp-结构 | P22: JT0807010100009 | Q22: 搭建部分-背景结构 | R22: 搭建部分-背景结构 木质背板 异形单面木质背景板/木结构，表面防火板，正面裱写真，含支撑及画面 制作 | S22: 26.4 | T22: 平方米 | U22: 1 | V22: 天 | W22: 235.84906 | X22: =S22*U22*W22 -> 6226.4151 | Y22: =X22-0 -> 6226.4151 | Z22: 新增需求内容 | AA22: 设计定稿后更新材质及尺寸 | AB22: 左侧书页：宽2.01m 高2.5m 厚度0.33m 面积计算：2×(0.6633+0.825+5.025)=13.03m² 右侧书页：宽2.07m 高2.5m 厚度0.33m 面积计算：2×(0.6831+0.825+5.175)=13.37m² 小计：13.03+13.37=26.4m² | AD22: 15 | AE22: 主dp-底座画面 | AF22: JT0807010250006 | AG22: 搭建部分-写真喷绘 | AH22: 搭建部分-写真喷绘 写真喷绘 进口3M车贴 /常规规格 制作 | AI22: 10.56 | AJ22: 平方米 | AK22: 1 | AL22: 天 | AM22: 60.377358 | AN22: =AI22*AK22*AM22 -> 637.58491 | AO22: =AN22-X28 -> 0
A23: 16 | B23: 主dp-支撑 | C23: JT0807010190017 | D23: 搭建部分-基础结构 | E23: 搭建部分-基础结构 钢结构 30*30方钢 制作 | F23: 20.1 | G23: 米 | H23: 1 | I23: 天 | J23: 39.839623 | K23: =F23*H23*J23 -> 800.77642 | L23: 钢结构支撑:3(4.2+2.5)=20.1m | N23: 16 | O23: 主dp-画面 | P23: JT0807010250006 | Q23: 搭建部分-写真喷绘 | R23: 搭建部分-写真喷绘 写真喷绘 进口3M车贴 /常规规格 制作 | S23: 0 | T23: 平方米 | U23: 0 | V23: 天 | W23: 60.377358 | X23: =S23*U23*W23 -> 0 | Y23: =X23-K21 -> -2329.3585 | Z23: 取消需求内容 | AA23: 设计定稿后更新材质及尺寸 | AD23: 16 | AE23: 互动点位1-大结构 | AF23: JT0807010100009 | AG23: 搭建部分-背景结构 | AH23: 搭建部分-背景结构 木质背板 异形单面木质背景板/木结构，表面防火板，正面裱写真，含支撑及画面 制作 | AI23: 15.46 | AJ23: 平方米 | AK23: 1 | AL23: 天 | AM23: 235.84906 | AN23: =AI23*AK23*AM23 -> 3646.2264 | AO23: =AN23-Y30 -> 0
A24: 17 | B24: 主dp-底座结构 | C24: JT0807010100010 | D24: 搭建部分-背景结构 | E24: 搭建部分-背景结构 木质背板 双面木质涂料背板/木结构，表面刷涂料，含支撑 制作 | F24: 5.2 | G24: 平方米 | H24: 1 | I24: 天 | J24: 295 | K24: =F24*H24*J24 -> 1534 | L24: 设计未定，尺寸预估，2(2*1+1*0.2+2*0.2)=5.2㎡ | N24: 17 | O24: 主dp-装饰画面 | P24: JT0807010250017 | Q24: 搭建部分-写真喷绘 | R24: 搭建部分-写真喷绘 写真喷绘 PVC板/裱高清,5MM板，含覆膜/常规规格 制作 | S24: 5 | T24: 平方米 | U24: 1 | V24: 天 | W24: 80 | X24: =S24*U24*W24 -> 400 | Y24: =X24-K22 -> -240 | Z24: 变更需求内容-导致费用减少 | AA24: 设计定稿后更新材质及尺寸 | AD24: 17 | AE24: 互动点位1-导台结构 | AF24: JT0807010100017 | AG24: 搭建部分-背景结构 | AH24: 搭建部分-背景结构 木质背板 单面木质背板/木结构 表面防火板，正面裱写真，含支撑及画面 制作 | AI24: 16.21 | AJ24: 平方米 | AK24: 1 | AL24: 天 | AM24: 187 | AN24: =AI24*AK24*AM24 -> 3031.27 | AO24: =AN24-X33 -> 0
A25: 18 | B25: 主dp-底座画面 | C25: JT0807010250006 | D25: 搭建部分-写真喷绘 | E25: 搭建部分-写真喷绘 写真喷绘 进口3M车贴 /常规规格 制作 | F25: 5.2 | G25: 平方米 | H25: 1 | I25: 天 | J25: 60.377358 | K25: =F25*H25*J25 -> 313.96226 | L25: 设计未定，尺寸预估 | N25: 18 | O25: 主dp-支撑 | P25: JT0807010190017 | Q25: 搭建部分-基础结构 | R25: 搭建部分-基础结构 钢结构 30*30方钢 制作 | S25: 9.42 | T25: 米 | U25: 1 | V25: 天 | W25: 39.839623 | X25: =S25*U25*W25 -> 375.28925 | Y25: =X25-K23 -> -425.48717 | Z25: 变更需求内容-导致费用减少 | AA25: 设计定稿后更新材质及尺寸 | AB25: 横杆2.2m*2+竖杆2.51m*2=9.42m | AD25: 18 | AE25: 互动点位1-装饰结构 | AF25: JT0807010100009 | AG25: 搭建部分-背景结构 | AH25: 搭建部分-背景结构 木质背板 异形单面木质背景板/木结构，表面防火板，正面裱写真，含支撑及画面 制作 | AI25: 9.28 | AJ25: 平方米 | AK25: 1 | AL25: 天 | AM25: 235.84906 | AN25: =AI25*AK25*AM25 -> 2188.6792 | AO25: =AN25-X35 -> 0
A26: 19 | B26: 互动点位1-结构 | C26: JT0807010100010 | D26: 搭建部分-背景结构 | E26: 搭建部分-背景结构 木质背板 双面木质涂料背板/木结构，表面刷涂料，含支撑 制作 | F26: 33.7 | G26: 平方米 | H26: 1 | I26: 天 | J26: 295 | K26: =F26*H26*J26 -> 9941.5 | L26: 2*(4.5*2.5+2.5*0.8+4.5*0.8)=33.7㎡ | N26: 19 | O26: 主dp-底座结构 | P26: JT0807010100010 | Q26: 搭建部分-背景结构 | R26: 搭建部分-背景结构 木质背板 双面木质涂料背板/木结构，表面刷涂料，含支撑 制作 | S26: 0 | T26: 平方米 | U26: 1 | V26: 天 | W26: 295 | X26: =S26*U26*W26 -> 0 | Y26: =X26-K24 -> -1534 | Z26: 取消需求内容 | AA26: 设计定稿后更新材质及尺寸 | AD26: 19 | AE26: 互动点位1-pvc画面 | AF26: JT0807010250017 | AG26: 搭建部分-写真喷绘 | AH26: 搭建部分-写真喷绘 写真喷绘 PVC板/裱高清,5MM板，含覆膜/常规规格 制作 | AI26: 1.49 | AJ26: 平方米 | AK26: 1 | AL26: 天 | AM26: 80 | AN26: =AI26*AK26*AM26 -> 119.2 | AO26: =AN26-X36 -> 0
A27: 20 | B27: 互动点位1-画面 | C27: JT0807010250006 | D27: 搭建部分-写真喷绘 | E27: 搭建部分-写真喷绘 写真喷绘 进口3M车贴 /常规规格 制作 | F27: 33.7 | G27: 平方米 | H27: 1 | I27: 天 | J27: 60.377358 | K27: =F27*H27*J27 -> 2034.717 | L27: 2*(4.5*2.5+2.5*0.8+4.5*0.8)=33.7㎡ | N27: 20 | O27: 主dp-底座结构 | P27: JT0807010100006 | Q27: 搭建部分-背景结构 | R27: 搭建部分-背景结构 木质背板 异形单面木质涂料背板/木结构，表面刷涂料，含支撑 制作 | S27: 10.56 | T27: 平方米 | U27: 1 | V27: 天 | W27: 240 | X27: =S27*U27*W27 -> 2534.4 | Y27: =X27-0 -> 2534.4 | Z27: 新增需求内容 | AA27: 设计定稿后更新材质及尺寸 | AB27: 尺寸:长2m 宽2m 高度0.1m 面积计算：2(2.2*2.2+2.2*0.1+2.2*0.1)=10.56㎡ | AD27: 20 | AE27: 互动点位1-立体字 | AF27: JT0807010210013 | AG27: 搭建部分-立体字 | AH27: 搭建部分-立体字 PVC立体字 常规材质/厚5MM ，高度300MM-600MM以内 制作 | AI27: 1.8 | AJ27: 延米 | AK27: 1 | AL27: 天 | AM27: 139.62 | AN27: =AI27*AK27*AM27 -> 251.316 | AO27: =AN27-X37 -> 0
A28: 21 | B28: 互动点位1-导台画面 | C28: JT0807010250006 | D28: 搭建部分-写真喷绘 | E28: 搭建部分-写真喷绘 写真喷绘 进口3M车贴 /常规规格 制作 | F28: 8 | G28: 平方米 | H28: 1 | I28: 天 | J28: 60.377358 | K28: =F28*H28*J28 -> 483.01887 | L28: 导台画面 | N28: 21 | O28: 主dp-底座画面 | P28: JT0807010250006 | Q28: 搭建部分-写真喷绘 | R28: 搭建部分-写真喷绘 写真喷绘 进口3M车贴 /常规规格 制作 | S28: 10.56 | T28: 平方米 | U28: 1 | V28: 天 | W28: 60.377358 | X28: =S28*U28*W28 -> 637.58491 | Y28: =X28-K25 -> 323.62264 | Z28: 变更需求内容-导致费用增加 | AA28: 设计定稿后更新材质及尺寸 | AB28: 尺寸:长2m 宽2m 高度0.1m 面积计算：2(2.2*2.2+2.2*0.1+2.2*0.1)=10.56㎡ | AD28: 21 | AE28: 互动点位2-结构 | AF28: JT0807010100009 | AG28: 搭建部分-背景结构 | AH28: 搭建部分-背景结构 木质背板 异形单面木质背景板/木结构，表面防火板，正面裱写真，含支撑及画面 制作 | AI28: 24.26 | AJ28: 平方米 | AK28: 1 | AL28: 天 | AM28: 235.84906 | AN28: =AI28*AK28*AM28 -> 5721.6981 | AO28: =AN28-X39 -> 0
A29: 22 | B29: 互动点位1-导台结构 | C29: JT0807010100010 | D29: 搭建部分-背景结构 | E29: 搭建部分-背景结构 木质背板 双面木质涂料背板/木结构，表面刷涂料，含支撑 制作 | F29: 8 | G29: 平方米 | H29: 1 | I29: 天 | J29: 295 | K29: =F29*H29*J29 -> 2360 | L29: 导台结构 | N29: 22 | O29: 互动点位1-大结构 | P29: JT0807010100010 | Q29: 搭建部分-背景结构 | R29: 搭建部分-背景结构 木质背板 双面木质涂料背板/木结构，表面刷涂料，含支撑 制作 | S29: 0 | T29: 平方米 | U29: 1 | V29: 天 | W29: 295 | X29: =S29*U29*W29 -> 0 | Y29: =X29-K26 -> -9941.5 | Z29: 取消需求内容 | AA29: 设计定稿后更新材质及尺寸 | AD29: 22 | AE29: 互动点位2-屋檐结构 | AF29: JT0807010100009 | AG29: 搭建部分-背景结构 | AH29: 搭建部分-背景结构 木质背板 异形单面木质背景板/木结构，表面防火板，正面裱写真，含支撑及画面 制作 | AI29: 12.46 | AJ29: 平方米 | AK29: 1 | AL29: 天 | AM29: 235.84906 | AN29: =AI29*AK29*AM29 -> 2938.6792 | AO29: =AN29-X43 -> 0
A30: 23 | B30: 互动点位1-导台支撑 | C30: JT0807010190017 | D30: 搭建部分-基础结构 | E30: 搭建部分-基础结构 钢结构 30*30方钢 制作 | F30: 10 | G30: 米 | H30: 1 | I30: 天 | J30: 39.839623 | K30: =F30*H30*J30 -> 398.39623 | L30: 支撑4*2+2=10m | N30: 23 | O30: 互动点位1-大结构 | P30: JT0807010100009 | Q30: 搭建部分-背景结构 | R30: 搭建部分-背景结构 木质背板 异形单面木质背景板/木结构，表面防火板，正面裱写真，含支撑及画面 制作 | S30: 15.46 | T30: 平方米 | U30: 1 | V30: 天 | W30: 235.84906 | X30: =S30*U30*W30 -> 3646.2264 | Y30: =X30-0 -> 3646.2264 | Z30: 新增需求内容 | AA30: 设计定稿后更新材质及尺寸 | AB30: 尺寸：3.5m宽 1.9m高 厚度0.2m 面积计算：2×(6.65+0.38+0.7)=15.46m² | AD30: 23 | AE30: 互动点位2-互动导台 | AF30: JT0807010270004 | AG30: 搭建部分-制作物 | AH30: 搭建部分-制作物 展台/接待台 木结构防火板或裱画面, 弧形 ,做门带锁/ 规格高1m以下, 径深60cm以内 制作 | AI30: 2.2 | AJ30: 延米 | AK30: 1 | AL30: 天 | AM30: 750 | AN30: =AI30*AK30*AM30 -> 1650 | AO30: =AN30-X44 -> 0
A31: 24 | B31: 互动点位1-装饰画面 | C31: JT0807010250017 | D31: 搭建部分-写真喷绘 | E31: 搭建部分-写真喷绘 写真喷绘 PVC板/裱高清,5MM板，含覆膜/常规规格 制作 | F31: 5 | G31: 平方米 | H31: 1 | I31: 天 | J31: 80 | K31: =F31*H31*J31 -> 400 | L31: 装饰雪弗板画面 | N31: 24 | O31: 互动点位1-画面 | P31: JT0807010250006 | Q31: 搭建部分-写真喷绘 | R31: 搭建部分-写真喷绘 写真喷绘 进口3M车贴 /常规规格 制作 | S31: 0 | T31: 平方米 | U31: 1 | V31: 天 | W31: 60.377358 | X31: =S31*U31*W31 -> 0 | Y31: =X31-K27 -> -2034.717 | Z31: 取消需求内容 | AA31: 设计定稿后更新材质及尺寸 | AD31: 24 | AE31: 互动点位2-装饰pvc | AF31: JT0807010250017 | AG31: 搭建部分-写真喷绘 | AH31: 搭建部分-写真喷绘 写真喷绘 PVC板/裱高清,5MM板，含覆膜/常规规格 制作 | AI31: 2.52 | AJ31: 平方米 | AK31: 1 | AL31: 天 | AM31: 80 | AN31: =AI31*AK31*AM31 -> 201.6 | AO31: =AN31-X45 -> 0
A32: 25 | B32: 互动点位1-pvc立体字 | C32: JT0807010210015 | D32: 搭建部分-立体字 | E32: 搭建部分-立体字 PVC立体字 常规材质/厚3MM ，高度300MM-600MM以内 制作 | F32: 4 | G32: 延米 | H32: 1 | I32: 天 | J32: 100 | K32: =F32*H32*J32 -> 400 | L32: pvc立体字 | N32: 25 | O32: 互动点位1-导台结构 | P32: JT0807010100010 | Q32: 搭建部分-背景结构 | R32: 搭建部分-背景结构 木质背板 双面木质涂料背板/木结构，表面刷涂料，含支撑 制作 | S32: 0 | T32: 平方米 | U32: 1 | V32: 天 | W32: 295 | X32: =S32*U32*W32 -> 0 | Y32: =X32-K29 -> -2360 | Z32: 取消需求内容 | AA32: 设计定稿后更新材质及尺寸 | AD32: 25 | AE32: 互动点位2-京东图书立体字 | AF32: JT0807010210013 | AG32: 搭建部分-立体字 | AH32: 搭建部分-立体字 PVC立体字 常规材质/厚5MM ，高度300MM-600MM以内 制作 | AI32: 3.26 | AJ32: 延米 | AK32: 1 | AL32: 天 | AM32: 139.62 | AN32: =AI32*AK32*AM32 -> 455.1612 | AO32: =AN32-X48 -> 0
A33: 26 | B33: 互动点位2-背板结构 | C33: JT0807010100010 | D33: 搭建部分-背景结构 | E33: 搭建部分-背景结构 木质背板 双面木质涂料背板/木结构，表面刷涂料，含支撑 制作 | F33: 35 | G33: 平方米 | H33: 1 | I33: 天 | J33: 295 | K33: =F33*H33*J33 -> 10325 | L33: 设计未定，尺寸预估；2*(5*2.3+2.3*0.8+0.8*5)=30.68㎡，预估损耗共计35㎡ | N33: 26 | O33: 互动点位1-导台结构 | P33: JT0807010100017 | Q33: 搭建部分-背景结构 | R33: 搭建部分-背景结构 木质背板 单面木质背板/木结构 表面防火板，正面裱写真，含支撑及画面 制作 | S33: 16.21 | T33: 平方米 | U33: 1 | V33: 天 | W33: 187 | X33: =S33*U33*W33 -> 3031.27 | Y33: =X33-0 -> 3031.27 | Z33: 新增需求内容 | AA33: 设计定稿后更新材质及尺寸 | AB33: 横面板尺寸：长3.3m 宽 1.9m高 厚度0.08m 面积计算：2×(6.27+0.264+0.152)=13.72 竖板尺寸：高0.82m 宽0.4m 厚度0.07m 3组 2×(0.328+0.0574+0.028）=0.83*3=2.49m² ， 总计：16.21m² | AD33: 26 | AE33: 书适圈点位-画面 | AF33: JT0807010250017 | AG33: 搭建部分-写真喷绘 | AH33: 搭建部分-写真喷绘 写真喷绘 PVC板/裱高清,5MM板，含覆膜/常规规格 制作 | AI33: 4.22 | AJ33: 平方米 | AK33: 1 | AL33: 天 | AM33: 80 | AN33: =AI33*AK33*AM33 -> 337.6 | AO33: =AN33-X49 -> 0
A34: 27 | B34: 互动点位2-背板画面 | C34: JT0807010250006 | D34: 搭建部分-写真喷绘 | E34: 搭建部分-写真喷绘 写真喷绘 进口3M车贴 /常规规格 制作 | F34: 35 | G34: 平方米 | H34: 1 | I34: 天 | J34: 60.377358 | K34: =F34*H34*J34 -> 2113.2075 | L34: 2*(5*2.3+2.3*0.8+0.8*5)=30.68㎡，预估损耗共计35㎡ | N34: 27 | O34: 互动点位1-导台画面 | P34: JT0807010250006 | Q34: 搭建部分-写真喷绘 | R34: 搭建部分-写真喷绘 写真喷绘 进口3M车贴 /常规规格 制作 | S34: 0 | T34: 平方米 | U34: 1 | V34: 天 | W34: 60.377358 | X34: =S34*U34*W34 -> 0 | Y34: =X34-K28 -> -483.01887 | Z34: 取消需求内容 | AA34: 设计定稿后更新材质及尺寸 | AD34: 27 | AE34: 书适圈点位-支撑 | AF34: JT0807010190017 | AG34: 搭建部分-基础结构 | AH34: 搭建部分-基础结构 钢结构 30*30方钢 制作 | AI34: 3.05 | AJ34: 米 | AK34: 1 | AL34: 天 | AM34: 39.839623 | AN34: =AI34*AK34*AM34 -> 121.51085 | AO34: =AN34-X50 -> 0
A35: 28 | B35: 互动点位2-背板支撑 | C35: JT0807010190017 | D35: 搭建部分-基础结构 | E35: 搭建部分-基础结构 钢结构 30*30方钢 制作 | F35: 14.6 | G35: 米 | H35: 1 | I35: 天 | J35: 39.839623 | K35: =F35*H35*J35 -> 581.65849 | L35: 5*2+2.3*2=14.6m | N35: 28 | O35: 互动点位1-装饰结构 | P35: JT0807010100009 | Q35: 搭建部分-背景结构 | R35: 搭建部分-背景结构 木质背板 异形单面木质背景板/木结构，表面防火板，正面裱写真，含支撑及画面 制作 | S35: 9.28 | T35: 平方米 | U35: 1 | V35: 天 | W35: 235.84906 | X35: =S35*U35*W35 -> 2188.6792 | Y35: =X35-0 -> 2188.6792 | Z35: 新增需求内容 | AA35: 设计定稿后更新材质及尺寸 | AB35: 尺寸:高1.9m 宽1.85m 厚度0.3m 2×(3.515+0.57+0.555)=9.28m² | AD35: 28 | AE35: 书适圈点位-配重 | AF35: JT0807010100017 | AG35: 搭建部分-背景结构 | AH35: 搭建部分-背景结构 木质背板 单面木质背板/木结构 表面防火板，正面裱写真，含支撑及画面 制作 | AI35: 1.42 | AJ35: 平方米 | AK35: 1 | AL35: 天 | AM35: 187 | AN35: =AI35*AK35*AM35 -> 265.54 | AO35: =AN35-X51 -> 0
A36: 29 | B36: 互动点位2-屋檐结构 | C36: JT0807010100010 | D36: 搭建部分-背景结构 | E36: 搭建部分-背景结构 木质背板 双面木质涂料背板/木结构，表面刷涂料，含支撑 制作 | F36: 10 | G36: 平方米 | H36: 1 | I36: 天 | J36: 295 | K36: =F36*H36*J36 -> 2950 | L36: 2*(2*1+1*0.5+2*0.5)=7㎡,该结构正反两面中间需要加固处理,合计为10㎡ | N36: 29 | O36: 互动点位1-pvc画面 | P36: JT0807010250017 | Q36: 搭建部分-写真喷绘 | R36: 搭建部分-写真喷绘 写真喷绘 PVC板/裱高清,5MM板，含覆膜/常规规格 制作 | S36: 1.49 | T36: 平方米 | U36: 1 | V36: 天 | W36: 80 | X36: =S36*U36*W36 -> 119.2 | Y36: =X36-K31 -> -280.8 | Z36: 变更需求内容-导致费用减少 | AA36: 设计定稿后更新材质及尺寸 | AB36: 尺寸:1.2*0.43+0.88*0.64+0.61*0.67=1.49㎡ | AD36: 29 | AE36: 入口处-结构 | AF36: JT0807010100009 | AG36: 搭建部分-背景结构 | AH36: 搭建部分-背景结构 木质背板 异形单面木质背景板/木结构，表面防火板，正面裱写真，含支撑及画面 制作 | AI36: 9.9 | AJ36: 平方米 | AK36: 1 | AL36: 天 | AM36: 235.84906 | AN36: =AI36*AK36*AM36 -> 2334.9057 | AO36: =AN36-X54 -> 0
A37: 30 | B37: 互动点位2-屋檐画面 | C37: JT0807010250006 | D37: 搭建部分-写真喷绘 | E37: 搭建部分-写真喷绘 写真喷绘 进口3M车贴 /常规规格 制作 | F37: 7 | G37: 平方米 | H37: 1 | I37: 天 | J37: 60.377358 | K37: =F37*H37*J37 -> 422.64151 | L37: 支撑4*2+2=10m | N37: 30 | O37: 互动点位1-立体字 | P37: JT0807010210013 | Q37: 搭建部分-立体字 | R37: 搭建部分-立体字 PVC立体字 常规材质/厚5MM ，高度300MM-600MM以内 制作 | S37: 1.8 | T37: 延米 | U37: 1 | V37: 天 | W37: 139.62 | X37: =S37*U37*W37 -> 251.316 | Y37: =X37-K32 -> -148.684 | Z37: 变更需求内容-导致费用减少 | AA37: 设计定稿后更新材质及尺寸 | AB37: 立体字尺寸:1.8m | AD37: 30 | AE37: 入口处-互动导台 | AF37: JT0807010270006 | AG37: 搭建部分-制作物 | AH37: 搭建部分-制作物 展台/接待台 木结构防火板或裱画面 ,高低柜形, 做门带锁/规格 高1m以下, 径深60cm以内 制作 | AI37: 1.2 | AJ37: 延米 | AK37: 1 | AL37: 天 | AM37: 750 | AN37: =AI37*AK37*AM37 -> 900 | AO37: =AN37-X59 -> 0
A38: 31 | B38: 互动点位2-互动导台 | C38: JT0807010270004 | D38: 搭建部分-制作物 | E38: 搭建部分-制作物 展台/接待台 木结构防火板或裱画面, 弧形 ,做门带锁/ 规格高1m以下, 径深60cm以内 制作 | F38: 2.2 | G38: 延米 | H38: 1 | I38: 天 | J38: 750 | K38: =F38*H38*J38 -> 1650 | L38: 互动导台长1.2m，预估损耗2.2m | N38: 31 | O38: 互动点位2-结构 | P38: JT0807010100010 | Q38: 搭建部分-背景结构 | R38: 搭建部分-背景结构 木质背板 双面木质涂料背板/木结构，表面刷涂料，含支撑 制作 | S38: 0 | T38: 平方米 | U38: 1 | V38: 天 | W38: 295 | X38: =S38*U38*W38 -> 0 | Y38: =X38-K33 -> -10325 | Z38: 取消需求内容 | AA38: 设计定稿后更新材质及尺寸 | AD38: 31 | AE38: 氛围物料-镜子结构+画面 | AF38: JT0807010100009 | AG38: 搭建部分-背景结构 | AH38: 搭建部分-背景结构 木质背板 异形单面木质背景板/木结构，表面防火板，正面裱写真，含支撑及画面 制作 | AI38: 11.04 | AJ38: 平方米 | AK38: 1 | AL38: 天 | AM38: 235.84906 | AN38: =AI38*AK38*AM38 -> 2603.7736 | AO38: =AN38-X62 -> 0
A39: 32 | B39: 互动点位2-导台底部结构 | C39: JT0807010100010 | D39: 搭建部分-背景结构 | E39: 搭建部分-背景结构 木质背板 双面木质涂料背板/木结构，表面刷涂料，含支撑 制作 | F39: 10.56 | G39: 平方米 | H39: 1 | I39: 天 | J39: 295 | K39: =F39*H39*J39 -> 3115.2 | L39: 2*(2.2*2.2+2.2*0.1+2.2*0.1)=10.56㎡ | N39: 32 | O39: 互动点位2-结构 | P39: JT0807010100009 | Q39: 搭建部分-背景结构 | R39: 搭建部分-背景结构 木质背板 异形单面木质背景板/木结构，表面防火板，正面裱写真，含支撑及画面 制作 | S39: 24.26 | T39: 平方米 | U39: 1 | V39: 天 | W39: 235.84906 | X39: =S39*U39*W39 -> 5721.6981 | Y39: =X39-0 -> 5721.6981 | Z39: 新增需求内容 | AA39: 设计定稿后更新材质及尺寸 | AB39: 尺寸：宽3.4m 高2.7m 厚0.5m 面积计算：2(3.4*2.7+3.4*0.5+2.7*0.5)=24.26㎡ | AD39: 32 | AE39: 氛围物料-镜子底座结构 | AF39: JT0807010100009 | AG39: 搭建部分-背景结构 | AH39: 搭建部分-背景结构 木质背板 异形单面木质背景板/木结构，表面防火板，正面裱写真，含支撑及画面 制作 | AI39: 5.96 | AJ39: 平方米 | AK39: 1 | AL39: 天 | AM39: 235.84906 | AN39: =AI39*AK39*AM39 -> 1405.6604 | AO39: =AN39-X65 -> 0
A40: 33 | B40: 互动点位2-导台底部画面 | C40: JT0807010250006 | D40: 搭建部分-写真喷绘 | E40: 搭建部分-写真喷绘 写真喷绘 进口3M车贴 /常规规格 制作 | F40: 10.56 | G40: 平方米 | H40: 1 | I40: 天 | J40: 60.377358 | K40: =F40*H40*J40 -> 637.58491 | L40: 2*(2.2*2.2+2.2*0.1+2.2*0.1)=10.56㎡ | N40: 33 | O40: 互动点位2-画面 | P40: JT0807010250006 | Q40: 搭建部分-写真喷绘 | R40: 搭建部分-写真喷绘 写真喷绘 进口3M车贴 /常规规格 制作 | S40: 0 | T40: 平方米 | U40: 1 | V40: 天 | W40: 60.377358 | X40: =S40*U40*W40 -> 0 | Y40: =X40-K34 -> -2113.2075 | Z40: 取消需求内容 | AA40: 设计定稿后更新材质及尺寸 | AD40: 33 | AE40: 氛围物料-灯管喷漆 | AF40: JT0807010190008 | AG40: 搭建部分-基础结构 | AH40: 搭建部分-基础结构 喷漆 三层喷漆，金属漆 制作 | AI40: 1 | AJ40: 平方米 | AK40: 1 | AL40: 套 | AM40: 101.885 | AN40: =AI40*AK40*AM40 -> 101.885 | AO40: =AN40-X66 -> 0
A41: 34 | B41: 互动点位2-装饰画面 | C41: JT0807010250017 | D41: 搭建部分-写真喷绘 | E41: 搭建部分-写真喷绘 写真喷绘 PVC板/裱高清,5MM板，含覆膜/常规规格 制作 | F41: 5 | G41: 平方米 | H41: 1 | I41: 天 | J41: 80 | K41: =F41*H41*J41 -> 400 | L41: 装饰互动雪弗板 | N41: 34 | O41: 互动点位2-屋檐结构 | P41: JT0807010100010 | Q41: 搭建部分-背景结构 | R41: 搭建部分-背景结构 木质背板 双面木质涂料背板/木结构，表面刷涂料，含支撑 制作 | S41: 0 | T41: 平方米 | U41: 1 | V41: 天 | W41: 295 | X41: =S41*U41*W41 -> 0 | Y41: =X41-K36 -> -2950 | Z41: 取消需求内容 | AA41: 设计定稿后更新材质及尺寸 | AD41: 34 | AE41: 氛围物料-灯管结构 | AF41: JT0807010190017 | AG41: 搭建部分-基础结构 | AH41: 搭建部分-基础结构 钢结构 30*30方钢 制作 | AI41: 3.32 | AJ41: 米 | AK41: 1 | AL41: 天 | AM41: 39.839623 | AN41: =AI41*AK41*AM41 -> 132.26755 | AO41: =AN41-X67 -> 0
A42: 35 | B42: 互动点位2-书单报纸 | C42: JT0807010250014 | D42: 搭建部分-写真喷绘 | E42: 搭建部分-写真喷绘 写真喷绘 背胶相纸/含覆膜/常规规格 制作 | F42: 54 | G42: 平方米 | H42: 1 | I42: 天 | J42: 40 | K42: =F42*H42*J42 -> 2160 | L42: 报纸定制，尺寸预估；0.45*0.2*100*6=54㎡ | N42: 35 | O42: 互动点位2-屋檐画面 | P42: JT0807010250006 | Q42: 搭建部分-写真喷绘 | R42: 搭建部分-写真喷绘 写真喷绘 进口3M车贴 /常规规格 制作 | S42: 0 | T42: 平方米 | U42: 1 | V42: 天 | W42: 60.377358 | X42: =S42*U42*W42 -> 0 | Y42: =X42-K37 -> -422.64151 | Z42: 取消需求内容 | AA42: 设计定稿后更新材质及尺寸 | AD42: 35 | AE42: 玩法路牌喷漆 | AF42: JT0807010190008 | AG42: 搭建部分-基础结构 | AH42: 搭建部分-基础结构 喷漆 三层喷漆，金属漆 制作 | AI42: 1 | AJ42: 平方米 | AK42: 4 | AL42: 套 | AM42: 101.885 | AN42: =AI42*AK42*AM42 -> 407.54 | AO42: =AN42-X69 -> 0
A43: 36 | B43: 互动点位京东图书立体字 | C43: JT0807010120026 | D43: 搭建部分-灯带 | E43: 搭建部分-灯带 无边发光字 侧边铝边，无边发光字，正面发光 制作 | F43: 3 | G43: 延米 | H43: 1 | I43: 天 | J43: 480 | K43: =F43*H43*J43 -> 1440 | L43: 立体字露出 | N43: 36 | O43: 互动点位2-屋檐结构 | P43: JT0807010100009 | Q43: 搭建部分-背景结构 | R43: 搭建部分-背景结构 木质背板 异形单面木质背景板/木结构，表面防火板，正面裱写真，含支撑及画面 制作 | S43: 12.46 | T43: 平方米 | U43: 1 | V43: 天 | W43: 235.84906 | X43: =S43*U43*W43 -> 2938.6792 | Y43: =X43-0 -> 2938.6792 | Z43: 新增需求内容 | AA43: 设计定稿后更新材质及尺寸 | AB43: 尺寸：长2.5m 宽1.15*2 厚度0.1m 2(2.5*0.1+2.5*2.3+2.3*0.1)=12.46㎡ | AD43: 36 | AE43: 玩法路牌底座配重 | AH43: 搭建制作-制作-钢结构-结构钢板配重-Q215钢板，切割焊接，厚度10mm | AI43: 0.6 | AJ43: 组 | AK43: 4 | AL43: 组 | AM43: 191 | AN43: =AI43*AK43*AM43 -> 458.4 | AO43: =AN43-X70 -> 0
A44: 37 | B44: 京东图书点位装饰画面 | C44: JT0807010250017 | D44: 搭建部分-写真喷绘 | E44: 搭建部分-写真喷绘 写真喷绘 PVC板/裱高清,5MM板，含覆膜/常规规格 制作 | F44: 4 | G44: 平方米 | H44: 1 | I44: 天 | J44: 80 | K44: =F44*H44*J44 -> 320 | L44: 装饰雪弗板 | N44: 37 | O44: 互动点位2-互动导台 | P44: JT0807010270004 | Q44: 搭建部分-制作物 | R44: 搭建部分-制作物 展台/接待台 木结构防火板或裱画面, 弧形 ,做门带锁/ 规格高1m以下, 径深60cm以内 制作 | S44: 2.2 | T44: 延米 | U44: 1 | V44: 天 | W44: 750 | X44: =S44*U44*W44 -> 1650 | Y44: =X44-K38 -> 0 | AB44: 弧形展开尺寸2.2m | AD44: 37 | AE44: 玩法路牌支撑 | AF44: JT0807010190017 | AG44: 搭建部分-基础结构 | AH44: 搭建部分-基础结构 钢结构 30*30方钢 制作 | AI44: 2 | AJ44: 米 | AK44: 4 | AL44: 套 | AM44: 39.839623 | AN44: =AI44*AK44*AM44 -> 318.71698 | AO44: =AN44-X71 -> 0
A45: 38 | B45: 入口处书架结构 | C45: JT0807010100010 | D45: 搭建部分-背景结构 | E45: 搭建部分-背景结构 木质背板 双面木质涂料背板/木结构，表面刷涂料，含支撑 制作 | F45: 10.5 | G45: 平方米 | H45: 1 | I45: 天 | J45: 295 | K45: =F45*H45*J45 -> 3097.5 | L45: 2*(1.7*2+2*0.5+1.7*0.5)=10.5㎡ | N45: 38 | O45: 互动点位2-装饰pvc | P45: JT0807010250017 | Q45: 搭建部分-写真喷绘 | R45: 搭建部分-写真喷绘 写真喷绘 PVC板/裱高清,5MM板，含覆膜/常规规格 制作 | S45: 2.52 | T45: 平方米 | U45: 1 | V45: 天 | W45: 80 | X45: =S45*U45*W45 -> 201.6 | Y45: =X45-K41 -> -198.4 | Z45: 变更需求内容-导致费用减少 | AA45: 设计定稿后更新材质及尺寸 | AB45: 1.26*1.62+1.3*0.37=2.52㎡ | AD45: 38 | AE45: 玩法路牌画面 | AF45: JT0807010250017 | AG45: 搭建部分-写真喷绘 | AH45: 搭建部分-写真喷绘 写真喷绘 PVC板/裱高清,5MM板，含覆膜/常规规格 制作 | AI45: 0.9 | AJ45: 平方米 | AK45: 4 | AL45: 套 | AM45: 80 | AN45: =AI45*AK45*AM45 -> 288 | AO45: =AN45-X72 -> 0
A46: 39 | B46: 入口处书架画面 | C46: JT0807010250006 | D46: 搭建部分-写真喷绘 | E46: 搭建部分-写真喷绘 写真喷绘 进口3M车贴 /常规规格 制作 | F46: 10.5 | G46: 平方米 | H46: 1 | I46: 天 | J46: 60.377358 | K46: =F46*H46*J46 -> 633.96226 | L46: 2*(1.7*2+2*0.5+1.7*0.5)=10.5㎡ | N46: 39 | O46: 互动点位2-书单报纸 | P46: JT0807010250014 | Q46: 搭建部分-写真喷绘 | R46: 搭建部分-写真喷绘 写真喷绘 背胶相纸/含覆膜/常规规格 制作 | S46: 0 | T46: 平方米 | U46: 1 | V46: 天 | W46: 40 | X46: =S46*U46*W46 -> 0 | Y46: =X46-K42 -> -2160 | Z46: 取消需求内容 | AA46: 设计定稿后更新材质及尺寸 | AD46: 39 | AE46: 手持kt | AF46: JT0807010250019 | AG46: 搭建部分-写真喷绘 | AH46: 搭建部分-写真喷绘 写真喷绘 KT板裱高清/含覆膜/常规规格 制作 | AI46: 5 | AJ46: 平方米 | AK46: 1 | AL46: 天 | AM46: 47.17 | AN46: =AI46*AK46*AM46 -> 235.85 | AO46: =AN46-X73 -> 0
A47: 40 | B47: 入口处书架支撑 | C47: JT0807010190017 | D47: 搭建部分-基础结构 | E47: 搭建部分-基础结构 钢结构 30*30方钢 制作 | F47: 7.4 | G47: 米 | H47: 1 | I47: 天 | J47: 39.839623 | K47: =F47*H47*J47 -> 294.81321 | L47: 1.7*2+2*2=7.4m | N47: 40 | O47: 互动点位2-立体字 | P47: JT0807010120026 | Q47: 搭建部分-灯带 | R47: 搭建部分-灯带 无边发光字 侧边铝边，无边发光字，正面发光 制作 | S47: 0 | T47: 延米 | U47: 1 | V47: 天 | W47: 480 | X47: =S47*U47*W47 -> 0 | Y47: =X47-K43 -> -1440 | Z47: 取消需求内容 | AA47: 设计定稿后更新材质及尺寸 | AD47: 40 | AE47: 搭建工人 | AF47: JT0807010230005 | AG47: 搭建部分-人工费用 | AH47: 搭建部分-人工费用 搭建人工 力工/常规服务要求 | AI47: 6 | AJ47: 人/天 | AK47: 2 | AL47: 天 | AM47: 200 | AN47: =AI47*AK47*AM47 -> 2400 | AO47: =AN47-X74 -> 0
A48: 41 | B48: 入口处装饰画面 | C48: JT0807010250017 | D48: 搭建部分-写真喷绘 | E48: 搭建部分-写真喷绘 写真喷绘 PVC板/裱高清,5MM板，含覆膜/常规规格 制作 | F48: 1 | G48: 平方米 | H48: 1 | I48: 天 | J48: 80 | K48: =F48*H48*J48 -> 80 | L48: 装饰雪弗板 | N48: 41 | O48: 互动点位2-京东图书立体字 | P48: JT0807010210013 | Q48: 搭建部分-立体字 | R48: 搭建部分-立体字 PVC立体字 常规材质/厚5MM ，高度300MM-600MM以内 制作 | S48: 3.26 | T48: 延米 | U48: 1 | V48: 天 | W48: 139.62 | X48: =S48*U48*W48 -> 455.1612 | Y48: =X48-0 -> 455.1612 | Z48: 新增需求内容 | AA48: 设计定稿后更新材质及尺寸 | AB48: 1.63*正反2组 | AD48: 41 | AE48: 搭建电工 | AF48: JT0807010230006 | AG48: 搭建部分-人工费用 | AH48: 搭建部分-人工费用 搭建人工 电工/常规服务要求 | AI48: 3 | AJ48: 人/天 | AK48: 2 | AL48: 天 | AM48: 260 | AN48: =AI48*AK48*AM48 -> 1560 | AO48: =AN48-X75 -> 0
A49: 42 | B49: 入口互动导台 | C49: JT0807010270006 | D49: 搭建部分-制作物 | E49: 搭建部分-制作物 展台/接待台 木结构防火板或裱画面 ,高低柜形, 做门带锁/规格 高1m以下, 径深60cm以内 制作 | F49: 1.2 | G49: 延米 | H49: 1 | I49: 天 | J49: 750 | K49: =F49*H49*J49 -> 900 | L49: 互动导台长1.2m | N49: 42 | O49: 书适圈点位-画面 | P49: JT0807010250017 | Q49: 搭建部分-写真喷绘 | R49: 搭建部分-写真喷绘 写真喷绘 PVC板/裱高清,5MM板，含覆膜/常规规格 制作 | S49: 4.22 | T49: 平方米 | U49: 1 | V49: 天 | W49: 80 | X49: =S49*U49*W49 -> 337.6 | Y49: =X49-K44 -> 17.6 | Z49: 变更需求内容-导致费用增加 | AA49: 设计定稿后更新材质及尺寸 | AB49: 1.21*1.75*2（双层）=2.11*2-=4.22㎡ | AD49: 42 | AE49: 搭建美工 | AF49: JT0807010230004 | AG49: 搭建部分-人工费用 | AH49: 搭建部分-人工费用 搭建人工 美工/常规服务要求 | AI49: 5 | AJ49: 人/天 | AK49: 2 | AL49: 天 | AM49: 280 | AN49: =AI49*AK49*AM49 -> 2800 | AO49: =AN49-X76 -> 0
A50: 43 | B50: 氛围物料-镜子结构 | C50: JT0807010100010 | D50: 搭建部分-背景结构 | E50: 搭建部分-背景结构 木质背板 双面木质涂料背板/木结构，表面刷涂料，含支撑 制作 | F50: 10 | G50: 平方米 | H50: 1 | I50: 天 | J50: 295 | K50: =F50*H50*J50 -> 2950 | L50: 2*(2.2*2.2+2.2*0.1+2.2*0.1)=9.84㎡，预估含损耗10㎡ | N50: 43 | O50: 书适圈点位-支撑 | P50: JT0807010190017 | Q50: 搭建部分-基础结构 | R50: 搭建部分-基础结构 钢结构 30*30方钢 制作 | S50: 3.05 | T50: 米 | U50: 1 | V50: 天 | W50: 39.839623 | X50: =S50*U50*W50 -> 121.51085 | Y50: =X50-0 -> 121.51085 | Z50: 新增需求内容 | AA50: 设计定稿后更新材质及尺寸 | AB50: 尺寸:1.75+0.8+0.5=3.05m | AD50: 43 | AE50: 撤场工人 | AF50: JT0807010230005 | AG50: 搭建部分-人工费用 | AH50: 搭建部分-人工费用 搭建人工 力工/常规服务要求 | AI50: 6 | AJ50: 人/天 | AK50: 1 | AL50: 天 | AM50: 200 | AN50: =AI50*AK50*AM50 -> 1200 | AO50: =AN50-X77 -> 0
A51: 44 | B51: 氛围物料-镜子画面 | C51: JT0807010250006 | D51: 搭建部分-写真喷绘 | E51: 搭建部分-写真喷绘 写真喷绘 进口3M车贴 /常规规格 制作 | F51: 10 | G51: 平方米 | H51: 1 | I51: 天 | J51: 60.377358 | K51: =F51*H51*J51 -> 603.77358 | L51: 2*(2.2*2.2+2.2*0.1+2.2*0.1)=9.84㎡，预估含损耗10㎡ | N51: 44 | O51: 书适圈点位-配重 | P51: JT0807010100017 | Q51: 搭建部分-背景结构 | R51: 搭建部分-背景结构 木质背板 单面木质背板/木结构 表面防火板，正面裱写真，含支撑及画面 制作 | S51: 1.42 | T51: 平方米 | U51: 1 | V51: 天 | W51: 187 | X51: =S51*U51*W51 -> 265.54 | Y51: =X51-0 -> 265.54 | Z51: 新增需求内容 | AA51: 设计定稿后更新材质及尺寸 | AB51: 尺寸:2(0.7*0.5+0.5*0.3+0.3*0.7)=1.42㎡ | AD51: 44 | AE51: pp夹折页背卡定制 | AH51: pp夹折页背卡定制,300g,白卡纸,压褶痕 | AI51: 100 | AJ51: 套 | AK51: 2 | AL51: 天 | AM51: 1 | AN51: =AI51*AK51*AM51 -> 200 | AO51: =AN51-X78 -> 0
A52: 45 | B52: 氛围物料-镜子 | C52: JT0807010190031 | D52: 搭建部分-基础结构 | E52: 搭建部分-基础结构 钢化玻璃 8mm厚刚面玻璃 制作 | F52: 3 | G52: 平方米 | H52: 1 | I52: 项 | J52: 169.905 | K52: =F52*H52*J52 -> 509.715 | L52: 设计未定，尺寸预估1.2*2.5=3㎡ | N52: 45 | O52: 入口处-结构 | P52: JT0807010100010 | Q52: 搭建部分-背景结构 | R52: 搭建部分-背景结构 木质背板 双面木质涂料背板/木结构，表面刷涂料，含支撑 制作 | S52: 0 | T52: 平方米 | U52: 1 | V52: 天 | W52: 295 | X52: =S52*U52*W52 -> 0 | Y52: =X52-K45 -> -3097.5 | Z52: 取消需求内容 | AA52: 设计定稿后更新材质及尺寸 | AD52: 45 | AE52: 盲盒诗歌卡片定制 | AH52: 异形盲盒诗歌卡片定制,300g白卡纸,覆哑膜 | AI52: 1000 | AJ52: 页 | AK52: 2 | AL52: 天 | AM52: 1 | AN52: =AI52*AK52*AM52 -> 2000 | AO52: =AN52-X79 -> 0
A53: 46 | B53: 氛围物料-镜子底座结构 | C53: JT0807010100010 | D53: 搭建部分-背景结构 | E53: 搭建部分-背景结构 木质背板 双面木质涂料背板/木结构，表面刷涂料，含支撑 制作 | F53: 11.94 | G53: 平方米 | H53: 1 | I53: 天 | J53: 295 | K53: =F53*H53*J53 -> 3522.3 | L53: 设计未定，尺寸待定；2*(2.5*2.2+2.5*0.1+2.2*0.1)=11.94㎡ | N53: 46 | O53: 入口处-画面 | P53: JT0807010250006 | Q53: 搭建部分-写真喷绘 | R53: 搭建部分-写真喷绘 写真喷绘 进口3M车贴 /常规规格 制作 | S53: 0 | T53: 平方米 | U53: 1 | V53: 天 | W53: 60.377358 | X53: =S53*U53*W53 -> 0 | Y53: =X53-K46 -> -633.96226 | Z53: 取消需求内容 | AA53: 设计定稿后更新材质及尺寸 | AB53: 尺寸:2(1.3*2+1.3*0.35+2*0.36)=7.58㎡ | AD53: 46 | AE53: 书单推荐卡片定制 | AH53: 异形书单推荐卡片定制,300g白卡纸,覆哑膜 | AI53: 1000 | AJ53: 页 | AK53: 2 | AL53: 天 | AM53: 1 | AN53: =AI53*AK53*AM53 -> 2000 | AO53: =AN53-X80 -> 0
A54: 47 | B54: 氛围物料-镜子底座画面 | C54: JT0807010250006 | D54: 搭建部分-写真喷绘 | E54: 搭建部分-写真喷绘 写真喷绘 进口3M车贴 /常规规格 制作 | F54: 11.94 | G54: 平方米 | H54: 1 | I54: 天 | J54: 60.377358 | K54: =F54*H54*J54 -> 720.90566 | L54: 设计未定，尺寸待定；2*(2.5*2.2+2.5*0.1+2.2*0.1)=11.94㎡ | N54: 47 | O54: 入口处-结构 | P54: JT0807010100009 | Q54: 搭建部分-背景结构 | R54: 搭建部分-背景结构 木质背板 异形单面木质背景板/木结构，表面防火板，正面裱写真，含支撑及画面 制作 | S54: 9.9 | T54: 平方米 | U54: 1 | V54: 天 | W54: 235.84906 | X54: =S54*U54*W54 -> 2334.9057 | Y54: =X54-0 -> 2334.9057 | Z54: 新增需求内容 | AA54: 设计定稿后更新材质及尺寸 | AB54: 尺寸：宽1.3m 高2m 厚度0.36m 2×(2.6+0.72+0.468)=7.58m² 隔板：1.3m*0.2m （内嵌安装）厚度0.02m *4组 2×(0.26+0.026+0.004)=0.58*4=2.32m²，小计9.9m² | AD54: 47 | AE54: 一米栏 | AF54: JT0807010180004 | AG54: 搭建部分-防护用品 | AH54: 搭建部分-防护用品 围档 可伸缩1米栏/常规规格 租赁 | AI54: 40 | AJ54: 个 | AK54: 2 | AL54: 天 | AM54: 12 | AN54: =AI54*AK54*AM54 -> 960 | AO54: =AN54-X82 -> 0
A55: 48 | B55: 氛围物料-灯管喷漆 | C55: JT0807010190008 | D55: 搭建部分-基础结构 | E55: 搭建部分-基础结构 喷漆 三层喷漆，金属漆 制作 | F55: 2 | G55: 平方米 | H55: 1 | I55: 套 | J55: 101.885 | K55: =F55*H55*J55 -> 203.77 | L55: 设计未定，费用预留 | N55: 48 | O55: 入口处-书架结构 | P55: JT0807010100010 | Q55: 搭建部分-背景结构 | R55: 搭建部分-背景结构 木质背板 双面木质涂料背板/木结构，表面刷涂料，含支撑 制作 | S55: 0 | T55: 平方米 | U55: 1 | V55: 天 | W55: 295 | X55: =S55*U55*W55 -> 0 | Y55: =X55-K45 -> -3097.5 | Z55: 取消需求内容 | AA55: 设计定稿后更新材质及尺寸 | AD55: 48 | AE55: 驻场工人 | AF55: JT0807010230004 | AG55: 搭建部分-人工费用 | AH55: 搭建部分-人工费用 搭建人工 美工/常规服务要求 | AI55: 1 | AJ55: 人/天 | AK55: 2 | AL55: 天 | AM55: 280 | AN55: =AI55*AK55*AM55 -> 560 | AO55: =AN55-0 -> 560
A56: 49 | B56: 氛围物料-灯管结构 | C56: JT0807010100005 | D56: 搭建部分-背景结构 | E56: 搭建部分-背景结构 木质背板 异形双面木质背板/木结构 表面防火板 正背面裱写真 含支撑及画面 制作 | F56: 2 | G56: 平方米 | H56: 1 | I56: 天 | J56: 339.62 | K56: =F56*H56*J56 -> 679.24 | L56: 设计未定，费用预留 | N56: 49 | O56: 入口处书架画面 | P56: JT0807010250006 | Q56: 搭建部分-写真喷绘 | R56: 搭建部分-写真喷绘 写真喷绘 进口3M车贴 /常规规格 制作 | S56: 0 | T56: 平方米 | U56: 1 | V56: 天 | W56: 60.377358 | X56: =S56*U56*W56 -> 0 | Y56: =X56-K46 -> -633.96226 | Z56: 取消需求内容 | AA56: 设计定稿后更新材质及尺寸 | AD56: 49 | AE56: 搭建物料及人员部分小计 | AF56: \ | AG56: \ | AH56: \ | AI56: \ | AJ56: \ | AK56: \ | AL56: \ | AM56: \ | AN56: =SUM(AN17:AN55) -> 63953.969 | AO56: =SUM(AO15:AO55) -> 560
A57: 50 | B57: 玩法路牌喷漆 | C57: JT0807010190008 | D57: 搭建部分-基础结构 | E57: 搭建部分-基础结构 喷漆 三层喷漆，金属漆 制作 | F57: 2 | G57: 平方米 | H57: 3 | I57: 套 | J57: 101.885 | K57: =F57*H57*J57 -> 611.31 | L57: 设计未定，费用预留 | N57: 50 | O57: 入口处书架支撑 | P57: JT0807010190017 | Q57: 搭建部分-基础结构 | R57: 搭建部分-基础结构 钢结构 30*30方钢 制作 | S57: 0 | T57: 米 | U57: 1 | V57: 天 | W57: 39.839623 | X57: =S57*U57*W57 -> 0 | Y57: =X57-K47 -> -294.81321 | Z57: 取消需求内容 | AA57: 设计定稿后更新材质及尺寸 | AD57: 50 | AE57: 云相册直播 | AF57: JT0807010010008 | AG57: AV部分-人工 | AH57: AV部分-人工 第三方人员及服务 图片直播 | AI57: 1 | AJ57: 人/天 | AK57: 2 | AL57: 天 | AM57: 800 | AN57: =AI57*AK57*AM57 -> 1600 | AO57: =AN57-X87 -> 0
A58: 51 | B58: 玩法路牌支撑 | C58: JT0807010190017 | D58: 搭建部分-基础结构 | E58: 搭建部分-基础结构 钢结构 30*30方钢 制作 | F58: 2 | G58: 米 | H58: 3 | I58: 套 | J58: 39.839623 | K58: =F58*H58*J58 -> 239.03774 | L58: 设计未定，费用预留 | N58: 51 | AD58: 51
A59: 52 | B59: 玩法路牌画面 | C59: JT0807010250017 | D59: 搭建部分-写真喷绘 | E59: 搭建部分-写真喷绘 写真喷绘 PVC板/裱高清,5MM板，含覆膜/常规规格 制作 | F59: 2 | G59: 平方米 | H59: 3 | I59: 套 | J59: 80 | K59: =F59*H59*J59 -> 480 | L59: 设计未定，费用预留 | N59: 52 | O59: 入口处-互动导台 | P59: JT0807010270006 | Q59: 搭建部分-制作物 | R59: 搭建部分-制作物 展台/接待台 木结构防火板或裱画面 ,高低柜形, 做门带锁/规格 高1m以下, 径深60cm以内 制作 | S59: 1.2 | T59: 延米 | U59: 1 | V59: 天 | W59: 750 | X59: =S59*U59*W59 -> 900 | Y59: =X59-K49 -> 0 | AB59: 1.2延米 | AD59: 52 | AE59: AV设备及人员部分小计 | AF59: \ | AG59: \ | AH59: \ | AI59: \ | AJ59: \ | AK59: \ | AL59: \ | AM59: \ | AN59: =SUM(AN57:AN57) -> 1600 | AO59: =SUM(AO57:AO57) -> 0
A60: 53 | B60: 手持kt | C60: JT0807010250019 | D60: 搭建部分-写真喷绘 | E60: 搭建部分-写真喷绘 写真喷绘 KT板裱高清/含覆膜/常规规格 制作 | F60: 5 | G60: 平方米 | H60: 1 | I60: 天 | J60: 47.17 | K60: =F60*H60*J60 -> 235.85 | L60: 设计未定，费用预留 | N60: 53 | O60: 氛围物料-镜子结构 | P60: JT0807010100010 | Q60: 搭建部分-背景结构 | R60: 搭建部分-背景结构 木质背板 双面木质涂料背板/木结构，表面刷涂料，含支撑 制作 | S60: 0 | T60: 平方米 | U60: 1 | V60: 天 | W60: 295 | X60: =S60*U60*W60 -> 0 | Y60: =X60-K50 -> -2950 | Z60: 取消需求内容 | AA60: 设计定稿后更新材质及尺寸 | AD60: 53 | AE60: 活动运营-兼职 | AF60: JT0807010280025 | AG60: 第三方人员及服务 | AH60: 第三方人员及服务 兼职 常规人员要求/10小时工作时间,含面试 | AI60: 6 | AJ60: 个 | AK60: 2 | AL60: 天 | AM60: 295 | AN60: =AI60*AK60*AM60 -> 3540 | AO60: =AN60-X94 -> 0
A61: 54 | B61: pp夹折页背卡定制 | E61: pp夹折页背卡定制,300g,白卡纸,压褶痕 | F61: 100 | G61: 套 | H61: 2 | I61: 天 | J61: 1.5 | K61: =F61*H61*J61 -> 300 | L61: 设计未定，费用预留 | N61: 54 | O61: 氛围物料-镜子画面 | P61: JT0807010250006 | Q61: 搭建部分-写真喷绘 | R61: 搭建部分-写真喷绘 写真喷绘 进口3M车贴 /常规规格 制作 | S61: 0 | T61: 平方米 | U61: 1 | V61: 天 | W61: 60.377358 | X61: =S61*U61*W61 -> 0 | Y61: =X61-K51 -> -603.77358 | Z61: 取消需求内容 | AA61: 设计定稿后更新材质及尺寸 | AD61: 54 | AE61: 周边打包兼职 | AF61: JT0807010280025 | AG61: 第三方人员及服务 | AH61: 第三方人员及服务 兼职 常规人员要求/10小时工作时间,含面试 | AI61: 2 | AJ61: 个 | AK61: 1 | AL61: 天 | AM61: 295 | AN61: =AI61*AK61*AM61 -> 590 | AO61: =AN61-X95 -> -1180 | AP61: 变更需求内容-导致费用减少
A62: 55 | B62: 盲盒诗歌卡片定制 | E62: 异形盲盒诗歌卡片定制,300g白卡纸,覆哑膜 | F62: 1000 | G62: 页 | H62: 2 | I62: 天 | J62: 1.5 | K62: =F62*H62*J62 -> 3000 | L62: 设计未定，费用预留 | N62: 55 | O62: 氛围物料-镜子结构+画面 | P62: JT0807010100009 | Q62: 搭建部分-背景结构 | R62: 搭建部分-背景结构 木质背板 异形单面木质背景板/木结构，表面防火板，正面裱写真，含支撑及画面 制作 | S62: 11.04 | T62: 平方米 | U62: 1 | V62: 天 | W62: 235.84906 | X62: =S62*U62*W62 -> 2603.7736 | Y62: =X62-0 -> 2603.7736 | Z62: 新增需求内容 | AA62: 设计定稿后更新材质及尺寸 | AB62: 左侧单程结构：宽0.86m 高1.8m 厚0.2m 2×(1.548+0.36+0.172)=4.16m² 右侧双层结构：宽0.68 高1.8m 厚0.2m *2双层 2×(1.224+0.36+0.136)=3.44m²*2=6.88m² 小计：11.04m² | AD62: 55 | AE62: 保洁 | AF62: JT0807010280038 | AG62: 第三方人员及服务 | AH62: 第三方人员及服务 保洁 常规人员要求/现场保洁 | AI62: 1 | AJ62: 个 | AK62: 2 | AL62: 天 | AM62: 250 | AN62: =AI62*AK62*AM62 -> 500 | AO62: =AN62-X96 -> 0
A63: 56 | B63: 书单推荐卡片定制 | E63: 异形书单推荐卡片定制,300g白卡纸,覆哑膜 | F63: 1000 | G63: 页 | H63: 2 | I63: 天 | J63: 1.5 | K63: =F63*H63*J63 -> 3000 | L63: 设计未定，费用预留 | N63: 56 | O63: 氛围物料-镜子底座结构 | P63: JT0807010100010 | Q63: 搭建部分-背景结构 | R63: 搭建部分-背景结构 木质背板 双面木质涂料背板/木结构，表面刷涂料，含支撑 制作 | S63: 0 | T63: 平方米 | U63: 1 | V63: 天 | W63: 295 | X63: =S63*U63*W63 -> 0 | Y63: =X63-K53 -> -3522.3 | Z63: 取消需求内容 | AA63: 设计定稿后更新材质及尺寸 | AD63: 56 | AE63: 安保 | AF63: JT0807010280039 | AG63: 第三方人员及服务 | AH63: 第三方人员及服务 保安人员 常规人员要求/现场安全及维持秩序 | AI63: 4 | AJ63: 个 | AK63: 2 | AL63: 天 | AM63: 300 | AN63: =AI63*AK63*AM63 -> 2400 | AO63: =AN63-X97 -> 0
A64: 57 | B64: 一米栏 | E64: 一米栏租赁 | F64: 40 | G64: 个 | H64: 2 | I64: 天 | J64: 28 | K64: =F64*H64*J64 -> 2240 | L64: 活动场地一米栏租赁 | N64: 57 | O64: 氛围物料-镜子底座画面 | P64: JT0807010250006 | Q64: 搭建部分-写真喷绘 | R64: 搭建部分-写真喷绘 写真喷绘 进口3M车贴 /常规规格 制作 | S64: 0 | T64: 平方米 | U64: 1 | V64: 天 | W64: 60.377358 | X64: =S64*U64*W64 -> 0 | Y64: =X64-K54 -> -720.90566 | Z64: 取消需求内容 | AA64: 设计定稿后更新材质及尺寸 | AD64: 57 | AE64: 摄影师 | AF64: JT0807010280019 | AG64: 第三方人员及服务 | AH64: 第三方人员及服务 摄影师 常规人员要求/活动全程跟拍 ,含机器 | AI64: 1 | AJ64: 个 | AK64: 2 | AL64: 天 | AM64: 1650 | AN64: =AI64*AK64*AM64 -> 3300 | AO64: =AN64-X98 -> 0
A65: 58 | B65: 搭建工人 | C65: JT0807010230005 | D65: 搭建部分-人工费用 | E65: 搭建部分-人工费用 搭建人工 力工/常规服务要求 | F65: 6 | G65: 人/天 | H65: 2 | I65: 天 | J65: 200 | K65: =F65*H65*J65 -> 2400 | L65: 搭建时间为22:00-次日08:00,夜班10h,因通宵搭建工人时长为2天 | N65: 58 | O65: 氛围物料-镜子底座结构 | P65: JT0807010100009 | Q65: 搭建部分-背景结构 | R65: 搭建部分-背景结构 木质背板 异形单面木质背景板/木结构，表面防火板，正面裱写真，含支撑及画面 制作 | S65: 5.96 | T65: 平方米 | U65: 1 | V65: 天 | W65: 235.84906 | X65: =S65*U65*W65 -> 1405.6604 | Y65: =X65-0 -> 1405.6604 | Z65: 新增需求内容 | AA65: 设计定稿后更新材质及尺寸 | AB65: 尺寸:2(1.8*1.31+1.8*0.2+1.31*0.2)=5.96㎡ | AD65: 58 | AE65: 搭建运输-进场车辆 | AF65: JT0807010280043 | AG65: 第三方人员及服务 | AH65: 第三方人员及服务 市内运输 6米厢式货车/常规服务要求 | AI65: 2 | AJ65: 次 | AK65: 1 | AL65: 辆 | AM65: 531.605 | AN65: =AI65*AK65*AM65 -> 1063.21 | AO65: =AN65-X99 -> 0 | AR65: 凭证14
A66: 59 | B66: 搭建电工 | C66: JT0807010230006 | D66: 搭建部分-人工费用 | E66: 搭建部分-人工费用 搭建人工 电工/常规服务要求 | F66: 3 | G66: 人/天 | H66: 2 | I66: 天 | J66: 260 | K66: =F66*H66*J66 -> 1560 | L66: 搭建时间为22:00-次日08:00,夜班10h,因通宵搭建工人时长为2天 | N66: 59 | O66: 氛围物料-灯管喷漆 | P66: JT0807010190008 | Q66: 搭建部分-基础结构 | R66: 搭建部分-基础结构 喷漆 三层喷漆，金属漆 制作 | S66: 1 | T66: 平方米 | U66: 1 | V66: 套 | W66: 101.885 | X66: =S66*U66*W66 -> 101.885 | Y66: =X66-K55 -> -101.885 | Z66: 变更需求内容-导致费用减少 | AA66: 设计定稿后更新材质及尺寸 | AD66: 59 | AE66: 搭建运输-进场车辆 | AF66: JT0807010280040 | AG66: 第三方人员及服务 | AH66: 第三方人员及服务 市内运输 金杯车/常规服务要求 | AI66: 1 | AJ66: 次 | AK66: 2 | AL66: 辆 | AM66: 240 | AN66: =AI66*AK66*AM66 -> 480 | AO66: =AN66-0 -> 480 | AP66: 新增需求内容 | AR66: 凭证14
A67: 60 | B67: 搭建美工 | C67: JT0807010230004 | D67: 搭建部分-人工费用 | E67: 搭建部分-人工费用 搭建人工 美工/常规服务要求 | F67: 5 | G67: 人/天 | H67: 2 | I67: 天 | J67: 280 | K67: =F67*H67*J67 -> 2800 | L67: 搭建时间为22:00-次日08:00,夜班10h,因通宵搭建工人时长为2天 | N67: 60 | O67: 氛围物料-灯管结构 | P67: JT0807010190017 | Q67: 搭建部分-基础结构 | R67: 搭建部分-基础结构 钢结构 30*30方钢 制作 | S67: 3.32 | T67: 米 | U67: 1 | V67: 天 | W67: 39.839623 | X67: =S67*U67*W67 -> 132.26755 | Y67: =X67-0 -> 132.26755 | Z67: 新增需求内容 | AA67: 设计定稿后更新材质及尺寸 | AB67: 尺寸：2.52+0.81=3.32m | AD67: 60 | AE67: 搭建运输-撤场车辆 | AF67: JT0807010280040 | AG67: 第三方人员及服务 | AH67: 第三方人员及服务 市内运输 金杯车/常规服务要求 | AI67: 1 | AJ67: 次 | AK67: 1 | AL67: 辆 | AM67: 240 | AN67: =AI67*AK67*AM67 -> 240 | AO67: =AN67-0 -> 240 | AP67: 新增需求内容 | AR67: 凭证15
O68: 氛围物料-灯管结构 | P68: JT0807010100005 | Q68: 搭建部分-背景结构 | R68: 搭建部分-背景结构 木质背板 异形双面木质背板/木结构 表面防火板 正背面裱写真 含支撑及画面 制作 | S68: 0 | T68: 平方米 | U68: 1 | V68: 天 | W68: 339.62 | X68: =S68*U68*W68 -> 0 | Y68: =X68-K56 -> -679.24 | Z68: 取消需求内容 | AA68: 设计定稿后更新材质及尺寸 | AD68: 61 | AE68: 搭建运输-撤场车辆 | AH68: 三轮平板车运输 | AI68: 1 | AJ68: 次 | AK68: 2 | AL68: 辆 | AM68: 220 | AN68: =AI68*AK68*AM68 -> 440 | AO68: =AN68-0 -> 440 | AP68: 新增需求内容 | AR68: 凭证15
A69: 61 | B69: 撤场工人 | C69: JT0807010230005 | D69: 搭建部分-人工费用 | E69: 搭建部分-人工费用 搭建人工 力工/常规服务要求 | F69: 6 | G69: 人/天 | H69: 1 | I69: 天 | J69: 200 | K69: =F69*H69*J69 -> 1200 | N69: 61 | O69: 玩法路牌喷漆 | P69: JT0807010190008 | Q69: 搭建部分-基础结构 | R69: 搭建部分-基础结构 喷漆 三层喷漆，金属漆 制作 | S69: 1 | T69: 平方米 | U69: 4 | V69: 套 | W69: 101.885 | X69: =S69*U69*W69 -> 407.54 | Y69: =X69-K57 -> -203.77 | Z69: 变更需求内容-导致费用增加 | AA69: 设计定稿后更新材质及尺寸 | AD69: 62
A70: 62 | B70: 。。。 | N70: 62 | O70: 玩法路牌底座配重 | R70: 搭建制作-制作-钢结构-结构钢板配重-Q215钢板，切割焊接，厚度10mm | S70: 0.6 | T70: 组 | U70: 4 | V70: 组 | W70: 191 | X70: =S70*U70*W70 -> 458.4 | Y70: =X70-0 -> 458.4 | Z70: 新增需求内容 | AA70: 设计定稿后更新材质及尺寸 | AB70: 0.6*3组 | AD70: 63
O71: 玩法路牌支撑 | P71: JT0807010190017 | Q71: 搭建部分-基础结构 | R71: 搭建部分-基础结构 钢结构 30*30方钢 制作 | S71: 2 | T71: 米 | U71: 4 | V71: 套 | W71: 39.839623 | X71: =S71*U71*W71 -> 318.71698 | Y71: =X71-K58 -> 79.679245 | Z71: 变更需求内容-导致费用增加 | AA71: 设计定稿后更新材质及尺寸 | AD71: 64 | AE71: 第三方人员部分小计 | AF71: \ | AG71: \ | AH71: \ | AI71: \ | AJ71: \ | AK71: \ | AL71: \ | AM71: \ | AN71: =SUM(AN60:AN70) -> 12553.21 | AO71: =SUM(AO60:AO70) -> -20
A72: 63 | B72: 搭建物料及人员部分小计 | C72: \ | D72: \ | E72: \ | F72: \ | G72: \ | H72: \ | I72: \ | J72: \ | K72: =SUM(K19:K70) -> 102573.2 | N72: 63 | O72: 玩法路牌画面 | P72: JT0807010250017 | Q72: 搭建部分-写真喷绘 | R72: 搭建部分-写真喷绘 写真喷绘 PVC板/裱高清,5MM板，含覆膜/常规规格 制作 | S72: 0.9 | T72: 平方米 | U72: 4 | V72: 套 | W72: 80 | X72: =S72*U72*W72 -> 288 | Y72: =X72-K59 -> -192 | Z72: 变更需求内容-导致费用减少 | AA72: 设计定稿后更新材质及尺寸 | AD72: 65 | AE72: 折叠反光定制 | AH72: 直径20cm,涤纶+定制手柄+定制包装袋 | AI72: 200 | AJ72: 个 | AK72: 2 | AL72: 天 | AM72: 4 | AN72: =AI72*AK72*AM72 -> 1600 | AO72: =AN72-X102 -> 0 | AR72: 凭证13
A73: 64 | B73: 云相册直播 | C73: JT0807010010008 | D73: AV部分-人工 | E73: AV部分-人工 第三方人员及服务 图片直播 | F73: 1 | G73: 人/天 | H73: 2 | I73: 天 | J73: 800 | K73: =F73*H73*J73 -> 1600 | N73: 64 | O73: 手持kt | P73: JT0807010250019 | Q73: 搭建部分-写真喷绘 | R73: 搭建部分-写真喷绘 写真喷绘 KT板裱高清/含覆膜/常规规格 制作 | S73: 5 | T73: 平方米 | U73: 1 | V73: 天 | W73: 47.17 | X73: =S73*U73*W73 -> 235.85 | Y73: =X73-K60 -> 0 | AD73: 66 | AE73: 牛皮杜邦纸袋定制 | AH73: 加急制作,35*40*10牛皮杜邦纸袋,有底无侧,牛皮光滑杜邦材质 | AI73: 75 | AJ73: 个 | AK73: 2 | AL73: 天 | AM73: 30 | AN73: =AI73*AK73*AM73 -> 4500 | AO73: =AN73-X103 -> 0 | AR73: 凭证13
A74: 65 | B74: 主会场-灯光 | C74: JT0807010020004 | D74: AV设备部分-灯光 | E74: AV设备部分-灯光 灯光架 Truss架 /规格400MM*400MM 租赁 | F74: 16 | G74: 米 | H74: 2 | I74: 天 | J74: 50 | K74: =F74*H74*J74 -> 1600 | N74: 65 | O74: 搭建工人 | P74: JT0807010230005 | Q74: 搭建部分-人工费用 | R74: 搭建部分-人工费用 搭建人工 力工/常规服务要求 | S74: 6 | T74: 人/天 | U74: 2 | V74: 天 | W74: 200 | X74: =S74*U74*W74 -> 2400 | Y74: =X74-K65 -> 0 | AD74: 67 | AE74: 硫酸书签 | AH74: 15*6白卡+四色硫酸纸书签 | AI74: 160 | AJ74: 个 | AK74: 2 | AL74: 天 | AM74: 3.5 | AN74: =AI74*AK74*AM74 -> 1120 | AO74: =AN74-X104 -> 0 | AR74: 凭证13
A75: 66 | B75: 主会场-灯光 | C75: JT0807010020044 | D75: AV设备部分-灯光 | E75: AV设备部分-灯光 AV设备部分-灯光 基础舞台灯光-电脑摇头切割灯 租赁 | F75: 4 | G75: 个 | H75: 2 | I75: 天 | J75: 437.26 | K75: =F75*H75*J75 -> 3498.08 | N75: 66 | O75: 搭建电工 | P75: JT0807010230006 | Q75: 搭建部分-人工费用 | R75: 搭建部分-人工费用 搭建人工 电工/常规服务要求 | S75: 3 | T75: 人/天 | U75: 2 | V75: 天 | W75: 260 | X75: =S75*U75*W75 -> 1560 | Y75: =X75-K66 -> 0 | AD75: 68 | AE75: 硫酸信封 | AH75: 信封采购 | AI75: 1 | AJ75: 个 | AK75: 1 | AL75: 项 | AM75: 150 | AN75: =AI75*AK75*AM75 -> 150 | AO75: =AN75-X105 -> 0 | AR75: 凭证13
A76: 67 | B76: 主会场-灯光 | C76: JT0807010020046 | D76: AV设备部分-灯光 | E76: AV设备部分-灯光 AV设备部分-灯光 基础舞台灯光-摇头LED Par灯 租赁 | F76: 8 | G76: 个 | H76: 2 | I76: 天 | J76: 116.60377 | K76: =F76*H76*J76 -> 1865.6604 | N76: 67 | O76: 搭建美工 | P76: JT0807010230004 | Q76: 搭建部分-人工费用 | R76: 搭建部分-人工费用 搭建人工 美工/常规服务要求 | S76: 5 | T76: 人/天 | U76: 2 | V76: 天 | W76: 280 | X76: =S76*U76*W76 -> 2800 | Y76: =X76-K67 -> 0 | AD76: 69 | AE76: 印章定制 | AH76: 火漆印定制,含开模 | AI76: 160 | AJ76: 个 | AK76: 2 | AL76: 天 | AM76: 2.8 | AN76: =AI76*AK76*AM76 -> 896 | AO76: =AN76-X106 -> 0 | AR76: 凭证13
A77: 68 | B77: 主会场-技术人员 | C77: JT0807010010005 | D77: AV部分-人工 | E77: AV部分-人工 灯光技术人员 国内 /含餐补 | F77: 1 | G77: 人/天 | H77: 2 | I77: 天 | J77: 400.4717 | K77: =F77*H77*J77 -> 800.9434 | N77: 68 | O77: 撤场工人 | P77: JT0807010230005 | Q77: 搭建部分-人工费用 | R77: 搭建部分-人工费用 搭建人工 力工/常规服务要求 | S77: 6 | T77: 人/天 | U77: 1 | V77: 天 | W77: 200 | X77: =S77*U77*W77 -> 1200 | Y77: =X77-K69 -> 0 | AD77: 70 | AE77: pp夹定制 | AH77: 亚克力pp夹,400个,直径5cm+4cm | AI77: 200 | AJ77: 个 | AK77: 2 | AL77: 天 | AM77: 6 | AN77: =AI77*AK77*AM77 -> 2400 | AO77: =AN77-X107 -> 0 | AR77: 凭证13
A78: 69 | B78: 。。。 | N78: 69 | O78: pp夹折页背卡定制 | R78: pp夹折页背卡定制,300g,白卡纸,压褶痕 | S78: 100 | T78: 套 | U78: 2 | V78: 天 | W78: 1 | X78: =S78*U78*W78 -> 200 | Y78: =X78-K61 -> -100 | Z78: 变更需求内容-导致费用减少 | AA78: 设计定稿后更新材质及尺寸 | AD78: 71 | AE78: opp袋 | AH78: opp袋 | AI78: 1 | AJ78: 个 | AK78: 1 | AL78: 项 | AM78: 150 | AN78: =AI78*AK78*AM78 -> 150 | AO78: =AN78-X108 -> 0 | AR78: 凭证13
A79: 70 | B79: AV设备及人员部分小计 | C79: \ | D79: \ | E79: \ | F79: \ | G79: \ | H79: \ | I79: \ | J79: \ | K79: =SUM(K73:K77) -> 9364.6838 | N79: 70 | O79: 盲盒诗歌卡片定制 | R79: 异形盲盒诗歌卡片定制,300g白卡纸,覆哑膜 | S79: 1000 | T79: 页 | U79: 2 | V79: 天 | W79: 1 | X79: =S79*U79*W79 -> 2000 | Y79: =X79-K62 -> -1000 | Z79: 变更需求内容-导致费用减少 | AA79: 设计定稿后更新材质及尺寸 | AD79: 72 | AE79: 亚克力置物架 | AH79: 亚克力置物架 | AI79: 0 | AJ79: 个 | AK79: 1 | AL79: 项 | AM79: 30 | AN79: =AI79*AK79*AM79 -> 0 | AO79: =AN79-X109 -> -300 | AP79: 取消需求内容
A80: 71 | B80: 活动运营-兼职 | C80: JT0807010280025 | D80: 第三方人员及服务 | E80: 第三方人员及服务 兼职 常规人员要求/10小时工作时间,含面试 | F80: 6 | G80: 个 | H80: 2 | I80: 天 | J80: 295 | K80: =F80*H80*J80 -> 3540 | L80: 6人兼职，2天 | N80: 71 | O80: 书单推荐卡片定制 | R80: 异形书单推荐卡片定制,300g白卡纸,覆哑膜 | S80: 1000 | T80: 页 | U80: 2 | V80: 天 | W80: 1 | X80: =S80*U80*W80 -> 2000 | Y80: =X80-K63 -> -1000 | Z80: 变更需求内容-导致费用减少 | AA80: 设计定稿后更新材质及尺寸 | AD80: 73 | AE80: 诗歌词条 | AH80: 盲盒诗歌词条采买 | AI80: 1 | AJ80: 项 | AK80: 1 | AL80: 项 | AM80: 373.09 | AN80: =AI80*AK80*AM80 -> 373.09 | AO80: =AN80-X91 -> 373.09 | AR80: 凭证6
A81: 72 | B81: 周边打包兼职 | C81: JT0807010280025 | D81: 第三方人员及服务 | E81: 第三方人员及服务 兼职 常规人员要求/10小时工作时间,含面试 | F81: 6 | G81: 个 | H81: 1 | I81: 天 | J81: 295 | K81: =F81*H81*J81 -> 1770 | N81: 72 | O81: 一米栏 | R81: 一米栏租赁 | S81: 0 | T81: 个 | U81: 0 | V81: 天 | W81: 28 | X81: =S81*U81*W81 -> 0 | Y81: =X81-K64 -> -2240 | Z81: 变更需求内容-导致费用减少 | AD81: 74 | AE81: 防雨物料 | AH81: 现场防雨物料(雨衣、雨布、雨伞等) | AI81: 1 | AJ81: 项 | AK81: 1 | AL81: 项 | AM81: 168.28 | AN81: =AI81*AK81*AM81 -> 168.28 | AO81: =AN81-0 -> 168.28 | AP81: 新增需求内容 | AR81: 凭证10
A82: 73 | B82: 保洁 | C82: JT0807010280038 | D82: 第三方人员及服务 | E82: 第三方人员及服务 保洁 常规人员要求/现场保洁 | F82: 1 | G82: 个 | H82: 2 | I82: 天 | J82: 250 | K82: =F82*H82*J82 -> 500 | N82: 73 | O82: 一米栏 | P82: JT0807010180004 | Q82: 搭建部分-防护用品 | R82: 搭建部分-防护用品 围档 可伸缩1米栏/常规规格 租赁 | S82: 40 | T82: 个 | U82: 2 | V82: 天 | W82: 12 | X82: =S82*U82*W82 -> 960 | Y82: =X82-0 -> 960 | Z82: 新增需求内容 | AD82: 75 | AE82: 遮阳伞采购 | AH82: 遮阳伞采购 | AI82: 1 | AJ82: 项 | AK82: 1 | AL82: 项 | AM82: 203.09 | AN82: =AI82*AK82*AM82 -> 203.09 | AO82: =AN82-0 -> 203.09 | AP82: 新增需求内容 | AR82: 凭证8
A83: 74 | B83: 安保 | C83: JT0807010280039 | D83: 第三方人员及服务 | E83: 第三方人员及服务 保安人员 常规人员要求/现场安全及维持秩序 | F83: 4 | G83: 个 | H83: 2 | I83: 天 | J83: 300 | K83: =F83*H83*J83 -> 2400 | N83: 74 | AD83: 76 | AE83: 防暑药物采购 | AH83: 藿香正气水采购 | AI83: 1 | AJ83: 项 | AK83: 1 | AL83: 项 | AM83: 153.24 | AN83: =AI83*AK83*AM83 -> 153.24 | AO83: =AN83-0 -> 153.24 | AP83: 新增需求内容 | AR83: 凭证9
A84: 75 | B84: 摄影师 | C84: JT0807010280019 | D84: 第三方人员及服务 | E84: 第三方人员及服务 摄影师 常规人员要求/活动全程跟拍 ,含机器 | F84: 1 | G84: 个 | H84: 2 | I84: 天 | J84: 1650 | K84: =F84*H84*J84 -> 3300 | N84: 75 | AD84: 77 | AE84: 现场搭建物料 | AH84: 现场小物料采买 | AI84: 1 | AJ84: 项 | AK84: 1 | AL84: 项 | AM84: 57.07 | AN84: =AI84*AK84*AM84 -> 57.07 | AO84: =AN84-0 -> 57.07 | AP84: 新增需求内容 | AR84: 凭证11
A85: 76 | B85: 搭建运输 | C85: JT0807010280043 | D85: 第三方人员及服务 | E85: 第三方人员及服务 市内运输 6米厢式货车/常规服务要求 | F85: 2 | G85: 次 | H85: 1 | I85: 辆 | J85: 531.605 | K85: =F85*H85*J85 -> 1063.21 | L85: 进撤场车辆 | N85: 76 | AD85: 78 | AE85: 现场书写物料 | AH85: 现场书写物料采买(亚克力架子、签字笔、胶带、胶棒等) | AI85: 1 | AJ85: 项 | AK85: 1 | AL85: 项 | AM85: 242.79 | AN85: =AI85*AK85*AM85 -> 242.79 | AO85: =AN85-0 -> 242.79 | AP85: 新增需求内容 | AR85: 凭证7
A86: 77 | B86: 。。。 | N86: 77 | O86: 搭建物料及人员部分小计 | P86: \ | Q86: \ | R86: \ | S86: \ | T86: \ | U86: \ | V86: \ | W86: \ | X86: =SUM(X19:X85) -> 63393.969 | Y86: =SUM(Y19:Y85) -> -37588.137 | AD86: 79
A87: 78 | B87: 第三方人员部分小计 | C87: \ | D87: \ | E87: \ | F87: \ | G87: \ | H87: \ | I87: \ | J87: \ | K87: =SUM(K80:K85) -> 12573.21 | N87: 78 | O87: 云相册直播 | P87: JT0807010010008 | Q87: AV部分-人工 | R87: AV部分-人工 第三方人员及服务 图片直播 | S87: 1 | T87: 人/天 | U87: 2 | V87: 天 | W87: 800 | X87: =S87*U87*W87 -> 1600 | Y87: =X87-K73 -> 0 | AD87: 80
A88: 79 | B88: 。。。 | N88: 79 | O88: 主会场-灯光 | P88: JT0807010020004 | Q88: AV设备部分-灯光 | R88: AV设备部分-灯光 灯光架 Truss架 /规格400MM*400MM 租赁 | S88: 0 | T88: 米 | U88: 0 | V88: 天 | W88: 50 | X88: =S88*U88*W88 -> 0 | Y88: =X88-K74 -> -1600 | Z88: 取消需求内容 | AD88: 81 | AE88: 后勤部分小计 | AF88: \ | AG88: \ | AH88: \ | AI88: \ | AJ88: \ | AK88: \ | AL88: \ | AM88: \ | AN88: =SUM(AN72:AN85) -> 12013.56 | AO88: 0
A89: 80 | B89: 后勤部分小计 | C89: \ | D89: \ | E89: \ | F89: \ | G89: \ | H89: \ | I89: \ | J89: \ | K89: 0 | N89: 80 | O89: 主会场-灯光 | P89: JT0807010020044 | Q89: AV设备部分-灯光 | R89: AV设备部分-灯光 AV设备部分-灯光 基础舞台灯光-电脑摇头切割灯 租赁 | S89: 0 | T89: 个 | U89: 0 | V89: 天 | W89: 437.26 | X89: =S89*U89*W89 -> 0 | Y89: =X89-K75 -> -3498.08 | Z89: 取消需求内容 | AD89: 82 | AE89: 。。。 | AO89: =X113-AN89 -> 0
A90: 81 | B90: 。。。 | N90: 81 | O90: 主会场-灯光 | P90: JT0807010020046 | Q90: AV设备部分-灯光 | R90: AV设备部分-灯光 AV设备部分-灯光 基础舞台灯光-摇头LED Par灯 租赁 | S90: 0 | T90: 个 | U90: 0 | V90: 天 | W90: 116.60377 | X90: =S90*U90*W90 -> 0 | Y90: =X90-K76 -> -1865.6604 | Z90: 取消需求内容 | AD90: 83 | AE90: 。。。 | AO90: =X114-AN90 -> 0
A91: 82 | B91: 视频部分小计 | C91: \ | D91: \ | E91: \ | F91: \ | G91: \ | H91: \ | I91: \ | J91: \ | K91: 0 | N91: 82 | O91: 主会场-技术人员 | P91: JT0807010010005 | Q91: AV部分-人工 | R91: AV部分-人工 灯光技术人员 国内 /含餐补 | S91: 0 | T91: 人/天 | U91: 0 | V91: 天 | W91: 400.4717 | X91: =S91*U91*W91 -> 0 | Y91: =X91-K77 -> -800.9434 | Z91: 取消需求内容 | AD91: 84 | AE91: 。。。 | AO91: =X115-AN91 -> 0
A92: 83 | B92: 创意策划执行部分 | C92: JT0807010090007 | D92: 创意策划执行 | E92: 创意策划执行 设计人员（平面） 主视觉设计 平面延展设计等 | F92: 1 | G92: 个项目 | H92: 1 | I92: 天 | J92: 2000 | K92: =F92*H92*J92 -> 2000 | N92: 83 | AD92: 85 | AE92: 视频部分小计 | AF92: \ | AG92: \ | AH92: \ | AI92: \ | AJ92: \ | AK92: \ | AL92: \ | AM92: \ | AN92: 0 | AO92: 0
A93: 84 | B93: 创意策划执行部分 | C93: JT0807010090008 | D93: 创意策划执行 | E93: 创意策划执行 设计人员（3D） 3D效果图设计 | F93: 1 | G93: 个项目 | H93: 1 | I93: 天 | J93: 1457.545 | K93: =F93*H93*J93 -> 1457.545 | N93: 84 | O93: AV设备及人员部分小计 | P93: \ | Q93: \ | R93: \ | S93: \ | T93: \ | U93: \ | V93: \ | W93: \ | X93: =SUM(X87:X91) -> 1600 | Y93: =SUM(Y87:Y91) -> -7764.6838 | AD93: 86 | AE93: 执行人员餐饮 | AF93: JT0807010090002 | AG93: 创意策划执行 | AH93: 创意策划执行 执行人员餐补 当地餐补 每日2餐 每餐上限为30元 | AI93: 4 | AJ93: 餐 | AK93: 4 | AL93: 天 | AM93: 19.73125 | AN93: =AI93*AK93*AM93 -> 315.7 | AO93: =AN93-X120 -> -137.1 | AP93: 变更需求内容-导致费用减少 | AR93: 凭证2
A94: 85 | B94: 创意策划执行部分 | C94: JT0807010090009 | D94: 创意策划执行 | E94: 创意策划执行 策划人员 包括创意方案 现场AV布置 展示搭建 会议流程控制等creative 服务内容 | F94: 1 | G94: 个项目 | H94: 1 | I94: 天 | J94: 1625 | K94: =F94*H94*J94 -> 1625 | L94: 三人每天两餐 | N94: 85 | O94: 活动运营-兼职 | P94: JT0807010280025 | Q94: 第三方人员及服务 | R94: 第三方人员及服务 兼职 常规人员要求/10小时工作时间,含面试 | S94: 6 | T94: 个 | U94: 2 | V94: 天 | W94: 295 | X94: =S94*U94*W94 -> 3540 | Y94: =X94-K80 -> 0 | AD94: 87 | AE94: 执行人员住宿 | AF94: JT0807010090005 | AG94: 创意策划执行 | AH94: 创意策划执行 执行人员住宿 异地住宿 二线城市上限 | AI94: 2 | AJ94: 间/晚 | AK94: 3 | AL94: 天 | AM94: 274.77 | AN94: =AI94*AK94*AM94 -> 1648.62 | AO94: =AN94-X121 -> -151.38 | AP94: 变更需求内容-导致费用减少 | AR94: 凭证1
A95: 86 | B95: 执行人员餐饮 | C95: JT0807010090002 | D95: 创意策划执行 | E95: 创意策划执行 执行人员餐补 当地餐补 每日2餐 每餐上限为30元 | F95: 6 | G95: 餐 | H95: 4 | I95: 天 | J95: 28.3 | K95: =F95*H95*J95 -> 679.2 | L95: 两间，3天，29、30 | N95: 86 | O95: 周边打包兼职 | P95: JT0807010280025 | Q95: 第三方人员及服务 | R95: 第三方人员及服务 兼职 常规人员要求/10小时工作时间,含面试 | S95: 6 | T95: 个 | U95: 1 | V95: 天 | W95: 295 | X95: =S95*U95*W95 -> 1770 | Y95: =X95-K81 -> 0 | Z95: 变更需求内容-导致费用减少 | AD95: 88 | AE95: 执行人员交通 | AF95: JT0807010090001 | AG95: 创意策划执行 | AH95: 创意策划执行 执行人员市内交通 凭票报销 | AI95: 2 | AJ95: 人/天 | AK95: 4 | AL95: 天 | AM95: 27.765 | AN95: =AI95*AK95*AM95 -> 222.12 | AO95: =AN95-X122 -> -155.24 | AR95: 凭证3
A96: 87 | B96: 执行人员住宿 | C96: JT0807010090005 | D96: 创意策划执行 | E96: 创意策划执行 执行人员住宿 异地住宿 二线城市上限 | F96: 2 | G96: 间/晚 | H96: 3 | I96: 天 | J96: 300 | K96: =F96*H96*J96 -> 1800 | L96: 三人四天 | N96: 87 | O96: 保洁 | P96: JT0807010280038 | Q96: 第三方人员及服务 | R96: 第三方人员及服务 保洁 常规人员要求/现场保洁 | S96: 1 | T96: 个 | U96: 2 | V96: 天 | W96: 250 | X96: =S96*U96*W96 -> 500 | Y96: =X96-K82 -> 0 | AD96: 89
A97: 88 | B97: 执行人员交通 | C97: JT0807010090001 | D97: 创意策划执行 | E97: 创意策划执行 执行人员市内交通 凭票报销 | F97: 3 | G97: 天 | H97: 4 | I97: 天 | J97: 47.17 | K97: =F97*H97*J97 -> 566.04 | N97: 88 | O97: 安保 | P97: JT0807010280039 | Q97: 第三方人员及服务 | R97: 第三方人员及服务 保安人员 常规人员要求/现场安全及维持秩序 | S97: 4 | T97: 个 | U97: 2 | V97: 天 | W97: 300 | X97: =S97*U97*W97 -> 2400 | Y97: =X97-K83 -> 0 | AD97: 90 | AE97: 创意策划执行部分小计 | AF97: \ | AG97: \ | AH97: \ | AI97: \ | AJ97: \ | AK97: \ | AL97: \ | AM97: \ | AN97: =SUM(AN93:AN95) -> 2186.44 | AO97: =SUM(AO93:AO95) -> -443.72
A98: 89 | B98: 。。。 | N98: 89 | O98: 摄影师 | P98: JT0807010280019 | Q98: 第三方人员及服务 | R98: 第三方人员及服务 摄影师 常规人员要求/活动全程跟拍 ,含机器 | S98: 1 | T98: 个 | U98: 2 | V98: 天 | W98: 1650 | X98: =S98*U98*W98 -> 3300 | Y98: =X98-K84 -> 0 | AD98: 91 | AE98: 执行人员机票 | AH98: 执行人员机票两人往返 | AI98: 2 | AJ98: 次 | AK98: 2 | AL98: 趟 | AM98: 615 | AN98: =AI98*AK98*AM98 -> 2460 | AO98: =AN98-X124 -> -1540 | AP98: 变更需求内容-导致费用减少 | AR98: 凭证4
A99: 90 | B99: 创意策划执行部分小计 | C99: \ | D99: \ | E99: \ | F99: \ | G99: \ | H99: \ | I99: \ | J99: \ | K99: =K92+K93+K95+K94+K97+K96 -> 8127.785 | N99: 90 | O99: 搭建运输 | P99: JT0807010280043 | Q99: 第三方人员及服务 | R99: 第三方人员及服务 市内运输 6米厢式货车/常规服务要求 | S99: 2 | T99: 次 | U99: 1 | V99: 辆 | W99: 531.605 | X99: =S99*U99*W99 -> 1063.21 | Y99: =X99-K85 -> 0 | AD99: 92
A100: 91 | B100: 执行人员机票 | F100: 3 | G100: 次 | H100: 2 | I100: 趟 | J100: 1000 | K100: =F100*H100*J100 -> 6000 | L100: 三人，来回两趟 | N100: 91 | AD100: 93 | AE100: 差旅部分小计 | AF100: \ | AG100: \ | AH100: \ | AI100: \ | AJ100: \ | AK100: \ | AL100: \ | AM100: \ | AN100: =SUM(AN98:AN99) -> 2460 | AO100: =SUM(AO98:AO99) -> -1540
...
